Workbook

Sheet TOP3277
A1: 网站名称 | B1: URL
A2: 百度 | B2: baidu.com
A3: 知乎 | B3: zhihu.com
A4: 腾讯网 | B4: qq.com
A5: 搜狐 | B5: sohu.com
A6: 哔哩哔哩 | B6: bilibili.com
A7: 网易网 | B7: 163.com
A8: 好搜 | B8: so.com
A9: 微信公众平台 | B9: mp.weixin.qq.com
A10: 抖音短视频 | B10: douyin.com
A11: 阿里巴巴 | B11: 1688.com
A12: 新浪微博 | B12: weibo.com
... A411: 起名网 | B411: yw11.com
A412: 17173 | B412: 17173.com
A413: 腾牛网 | B413: qqtn.com
A414: 工具查 | B414: gjcha.com
A415: 雪球网 | B415: xueqiu.com
A416: 星座屋网站 | B416: xzw.com
A417: 顺企网 | B417: 11467.com
A418: 文档投稿赚钱 | B418: book118.com
A419: 卜易居免费算命 | B419: buyiju.com
A420: 中国广播网 | B420: cnr.cn
A421: 律师 | B421: 64365.com
A422: 豆丁 | B422: docin.com
A423: 猫眼电影 | B423: maoyan.com
A424: 海词网 | B424: dict.cn
... A2778: 小飞兔软件 | B2778: xftsoft.com

Sheet 原始数据
A1: 网站名称 | B1: URL | C1: 全网流量总和左 | D1: 全网流量总和右 | E1: 站长之家平均流量 | F1: 百度来路左 | G1: 百度来路右 | H1: 爱站平均流量
A2: 重庆分类目录网 | B2: 023dir.com | C2: 25363 | D2: 40515 | E2: =SUM(C2,D2)/2 -> 32939 | F2: 10118 | G2: 15038 | H2: =SUM(F2,G2)/2 -> 12578
A3: 大连海岛旅游网 | B3: 0411hd.com | C3: 11313 | D3: 18071 | E3: =SUM(C3,D3)/2 -> 14692 | F3: 5579 | G3: 7656 | H3: =SUM(F3,G3)/2 -> 6617.5
A4: 合肥顺驰电子科技 | B4: 0551soft.com | C4: 0 | D4: 0 | E4: =SUM(C4,D4)/2 -> 0 | F4: 0 | G4: 0 | H4: =SUM(F4,G4)/2 -> 0
A5: 厦门创易网 | B5: 0592ui.com | C5: 30 | D5: 48 | E5: =SUM(C5,D5)/2 -> 39 | F5: 46 | G5: 56 | H5: =SUM(F5,G5)/2 -> 51
A6: 零度软件园 | B6: 05sun.net | C6: 6 | D6: 10 | E6: =SUM(C6,D6)/2 -> 8 | F6: 7 | G6: 10 | H6: =SUM(F6,G6)/2 -> 8.5
A7: 珠宝网 | B7: 0755zb.com | C7: 23846 | D7: 38092 | E7: =SUM(C7,D7)/2 -> 30969 | F7: 6277 | G7: 9730 | H7: =SUM(F7,G7)/2 -> 8003.5
A8: 壮游奇迹MU特色专区 | B8: 1000uc.com | C8: 3635 | D8: 5809 | E8: =SUM(C8,D8)/2 -> 4722 | F8: 4182 | G8: 6084 | H8: =SUM(F8,G8)/2 -> 5133
A9: 千助北京网站建设公司 | B9: 1000zhu.com | C9: 75 | D9: 121 | E9: =SUM(C9,D9)/2 -> 98 | F9: 38 | G9: 55 | H9: =SUM(F9,G9)/2 -> 46.5
A10: 中国联通网上营业厅 | B10: 10010.com | C10: 83211 | D10: 132923 | E10: =SUM(C10,D10)/2 -> 108067 | F10: 22470 | G10: 31833 | H10: =SUM(F10,G10)/2 -> 27151.5
A11: 中国移动 | B11: 10086.cn | C11: 437548 | D11: 698940 | E11: =SUM(C11,D11)/2 -> 568244 | F11: 98968 | G11: 139226 | H11: =SUM(F11,G11)/2 -> 119097
A12: 百田网 | B12: 100bt.com | C12: 15928 | D12: 25444 | E12: =SUM(C12,D12)/2 -> 20686 | F12: 7025 | G12: 9186 | H12: =SUM(F12,G12)/2 -> 8105.5
A13: 生意社 | B13: 100ppi.com | C13: 41666 | D13: 66558 | E13: =SUM(C13,D13)/2 -> 54112 | F13: 4117 | G13: 6391 | H13: =SUM(F13,G13)/2 -> 5254
... A272: 雅昌艺术网 | B272: artron.net | C272: 24660 | D272: 39394 | E272: =SUM(C272,D272)/2 -> 32027 | F272: 8362 | G272: 12609 | H272: =SUM(F272,G272)/2 -> 10485.5
A273: 百度应用 | B273: as.baidu.com | E273: =SUM(C273,D273)/2 -> 0 | F273: 33723 | G273: 110439 | H273: =SUM(F273,G273)/2 -> 72081
A274: 爱思资源网 | B274: aseoe.com | C274: 23 | D274: 37 | E274: =SUM(C274,D274)/2 -> 30 | F274: 14 | G274: 22 | H274: =SUM(F274,G274)/2 -> 18
A275: 阜宁县安顺房屋平移 | B275: asfwpy.com | C275: 63 | D275: 99 | E275: =SUM(C275,D275)/2 -> 81 | F275: 8 | G275: 12 | H275: =SUM(F275,G275)/2 -> 10
A276: 39问医生 | B276: ask.39.net | C276: 51738 | D276: 82644 | E276: =SUM(C276,D276)/2 -> 67191 | F276: 37190 | G276: 45476 | H276: =SUM(F276,G276)/2 -> 41333
A277: 家庭医生 | B277: ask.familydoctor.com.cn | C277: 11589 | D277: 18515 | E277: =SUM(C277,D277)/2 -> 15052 | F277: 6323 | G277: 8946 | H277: =SUM(F277,G277)/2 -> 7634.5
A278: 问答 | B278: ask.zol.com.cn | C278: 41835 | D278: 66827 | E278: =SUM(C278,D278)/2 -> 54331 | F278: 76549 | G278: 115036 | H278: =SUM(F278,G278)/2 -> 95792.5
A279: 中商情报 | B279: askci.com | C279: 21206 | D279: 33877 | E279: =SUM(C279,D279)/2 -> 27541.5 | F279: 5072 | G279: 7933 | H279: =SUM(F279,G279)/2 -> 6502.5
A280: 易云同步分享盘 我的资料存储小站 | B280: asytech.cn | C280: 101 | D280: 161 | E280: =SUM(C280,D280)/2 -> 131 | F280: 4 | G280: 7 | H280: =SUM(F280,G280)/2 -> 5.5
A281: 安拓盈智能科技 | B281: atyzn.com | C281: 1 | D281: 1 | E281: =SUM(C281,D281)/2 -> 1 | F281: 1 | G281: 1 | H281: =SUM(F281,G281)/2 -> 1
A282: 澳柯玛电动车 | B282: aucma-ev.com | C282: 28582 | D282: 45656 | E282: =SUM(C282,D282)/2 -> 37119 | F282: 5145 | G282: 7876 | H282: =SUM(F282,G282)/2 -> 6510.5
A283: 一汽-大众奥迪 | B283: audi.cn | C283: 106111 | D283: 169502 | E283: =SUM(C283,D283)/2 -> 137806.5 | F283: 12669 | G283: 19411 | H283: =SUM(F283,G283)/2 -> 16040
A284: 杭州奥格工业设计 | B284: augid.cn | C284: 2 | D284: 2 | E284: =SUM(C284,D284)/2 -> 2 | F284: 2 | G284: 3 | H284: =SUM(F284,G284)/2 -> 2.5
A285: 上海昊量光电设备 | B285: auniontech.com | C285: 271 | D285: 431 | E285: =SUM(C285,D285)/2 -> 351 | F285: 36 | G285: 57 | H285: =SUM(F285,G285)/2 -> 46.5
... A295: 顺企网公司 | B295: b2b.11467.com | C295: 6649 | D295: 10623 | E295: =SUM(C295,D295)/2 -> 8636 | F295: 3851 | G295: 5993 | H295: =SUM(F295,G295)/2 -> 4922
A296: 爱采购 | B296: b2b.baidu.com | E296: =SUM(C296,D296)/2 -> 0 | F296: 2419100 | G296: 3368074 | H296: =SUM(F296,G296)/2 -> 2893587
A297: 中国B2B交易平台 | B297: b2b.biz | C297: 5431 | D297: 8677 | E297: =SUM(C297,D297)/2 -> 7054 | F297: 5565 | G297: 8336 | H297: =SUM(F297,G297)/2 -> 6950.5
A298: 黄页88公司名录网 | B298: b2b.huangye88.com | C298: 20002 | D298: 31952 | E298: =SUM(C298,D298)/2 -> 25977 | F298: 20195 | G298: 25671 | H298: =SUM(F298,G298)/2 -> 22933
A299: 拔草哦 | B299: bacaoo.com | C299: 25432 | D299: 40626 | E299: =SUM(C299,D299)/2 -> 33029 | F299: 10470 | G299: 16949 | H299: =SUM(F299,G299)/2 -> 13709.5
A300: 八卦帝 | B300: baguadi.com | C300: 2642 | D300: 4222 | E300: =SUM(C300,D300)/2 -> 3432 | F300: 5446 | G300: 8870 | H300: =SUM(F300,G300)/2 -> 7158
A301: 百度 | B301: baidu.com | E301: =SUM(C301,D301)/2 -> 0 | F301: 119665456 | G301: 177051487 | H301: =SUM(F301,G301)/2 -> 1.4835847e+08
A302: 中国天气站 | B302: baidu.weather.com.cn | C302: 869983 | D302: 1389715 | E302: =SUM(C302,D302)/2 -> 1129849 | F302: 34054 | G302: 74508 | H302: =SUM(F302,G302)/2 -> 54281
A303: 百和软件官网 | B303: baihesoft.com | C303: 9 | D303: 15 | E303: =SUM(C303,D303)/2 -> 12 | F303: 3 | G303: 4 | H303: =SUM(F303,G303)/2 -> 3.5
A304: 百家号 | B304: baijiahao.baidu.com | E304: =SUM(C304,D304)/2 -> 0 | F304: 28563706 | G304: 40516775 | H304: =SUM(F304,G304)/2 -> 34540240
A305: 百度百科 | B305: baike.baidu.com | E305: =SUM(C305,D305)/2 -> 0 | F305: 27483221 | G305: 32825411 | H305: =SUM(F305,G305)/2 -> 30154316
A306: 会计百科 | B306: baike.kuaiji.com | C306: 83063 | D306: 132685 | E306: =SUM(C306,D306)/2 -> 107874 | F306: 3682 | G306: 9620 | H306: =SUM(F306,G306)/2 -> 6651
A307: 太平洋汽车网汽车百科 | B307: baike.pcauto.com.cn | C307: 75378 | D307: 120410 | E307: =SUM(C307,D307)/2 -> 97894 | F307: 28853 | G307: 38513 | H307: =SUM(F307,G307)/2 -> 33683
A308: 搜狗百科 | B308: baike.sogou.com | C308: 5320652 | D308: 8499224 | E308: =SUM(C308,D308)/2 -> 6909938 | F308: 16263 | G308: 22467 | H308: =SUM(F308,G308)/2 -> 19365
A309: 百贸网 | B309: baimao.com | C309: 6761 | D309: 10799 | E309: =SUM(C309,D309)/2 -> 8780 | F309: 7413 | G309: 11753 | H309: =SUM(F309,G309)/2 -> 9583
A310: 百度视频搜索网站 | B310: baishi.baidu.com | E310: =SUM(C310,D310)/2 -> 0 | F310: 28684 | G310: 38567 | H310: =SUM(F310,G310)/2 -> 33625.5
A311: 百姓网 | B311: baixing.com | C311: 72342 | D311: 115558 | E311: =SUM(C311,D311)/2 -> 93950 | F311: 46551 | G311: 61838 | H311: =SUM(F311,G311)/2 -> 54194.5
A312: 百修网 | B312: baixiu.org | C312: 41165 | D312: 65757 | E312: =SUM(C312,D312)/2 -> 53461 | F312: 11582 | G312: 17450 | H312: =SUM(F312,G312)/2 -> 14516
A313: 紫光通执法办案管理系统 | B313: bananxitong.com | C313: 1 | D313: 1 | E313: =SUM(C313,D313)/2 -> 1 | F313: 2 | G313: 3 | H313: =SUM(F313,G313)/2 -> 2.5
A314: 半岛网 | B314: bandao.cn | C314: 46954 | D314: 75006 | E314: =SUM(C314,D314)/2 -> 60980 | F314: 10819 | G314: 16051 | H314: =SUM(F314,G314)/2 -> 13435
A315: 交通银行 | B315: bankcomm.com | C315: 57356 | D315: 91618 | E315: =SUM(C315,D315)/2 -> 74487 | F315: 14479 | G315: 20191 | H315: =SUM(F315,G315)/2 -> 17335
A316: 360软件宝库 | B316: baoku.360.cn | C316: 688288 | D316: 1099476 | E316: =SUM(C316,D316)/2 -> 893882 | F316: 437 | G316: 710 | H316: =SUM(F316,G316)/2 -> 573.5
A317: 同花顺金融网站 | B317: basic.10jqka.com.cn | C317: 85798 | D317: 137054 | E317: =SUM(C317,D317)/2 -> 111426 | F317: 20200 | G317: 27910 | H317: =SUM(F317,G317)/2 -> 24055
A318: 八通网 | B318: bato.cn | C318: 105151 | D318: 167969 | E318: =SUM(C318,D318)/2 -> 136560 | F318: 138088 | G318: 201462 | H318: =SUM(F318,G318)/2 -> 169775
A319: 战网 | B319: battlenet.com.cn | C319: 26780 | D319: 42780 | E319: =SUM(C319,D319)/2 -> 34780 | F319: 5769 | G319: 8616 | H319: =SUM(F319,G319)/2 -> 7192.5
A320: 中文期刊 | B320: baywatch.cn | C320: 12268 | D320: 19596 | E320: =SUM(C320,D320)/2 -> 15932 | F320: 17053 | G320: 26418 | H320: =SUM(F320,G320)/2 -> 21735.5
A321: ps教程论坛 | B321: bbs.16xx8.com | C321: 238 | D321: 378 | E321: =SUM(C321,D321)/2 -> 308 | F321: 18 | G321: 26 | H321: =SUM(F321,G321)/2 -> 22
A322: 电子发烧友论坛 | B322: bbs.elecfans.com | C322: 12540 | D322: 20030 | E322: =SUM(C322,D322)/2 -> 16285 | F322: 4994 | G322: 6767 | H322: =SUM(F322,G322)/2 -> 5880.5
... A373: 程序猿DD | B373: blog.didispace.com | C373: 196 | D373: 314 | E373: =SUM(C373,D373)/2 -> 255 | F373: 2 | G373: 2 | H373: =SUM(F373,G373)/2 -> 2
A374: 新浪博客首页 | B374: blog.sina.com.cn | E374: =SUM(C374,D374)/2 -> 0 | F374: 24742 | G374: 33923 | H374: =SUM(F374,G374)/2 -> 29332.5
A375: 博客中国 | B375: blogchina.com | C375: 5356 | D375: 8554 | E375: =SUM(C375,D375)/2 -> 6955 | F375: 5284 | G375: 7856 | H375: =SUM(F375,G375)/2 -> 6570
A376: BlogJava | B376: blogjava.net | C376: 857 | D376: 1369 | E376: =SUM(C376,D376)/2 -> 1113 | F376: 453 | G376: 638 | H376: =SUM(F376,G376)/2 -> 545.5
A377: 北京蓝旷科技 | B377: bluemineai.com | C377: 8 | D377: 14 | E377: =SUM(C377,D377)/2 -> 11 | F377: 0 | G377: 0 | H377: =SUM(F377,G377)/2 -> 0
A378: 中国建材网站 | B378: bmlink.com | C378: 39314 | D378: 62800 | E378: =SUM(C378,D378)/2 -> 51057 | F378: 25414 | G378: 35476 | H378: =SUM(F378,G378)/2 -> 30445
A379: 宝马 | B379: bmw.com.cn | C379: 48294 | D379: 77144 | E379: =SUM(C379,D379)/2 -> 62719 | F379: 11016 | G379: 16335 | H379: =SUM(F379,G379)/2 -> 13675.5
A380: 剑灵 | B380: bns.17173.com | C380: 1481 | D380: 2367 | E380: =SUM(C380,D380)/2 -> 1924 | F380: 4517 | G380: 6861 | H380: =SUM(F380,G380)/2 -> 5689
A381: 山东布谷鸟网络科技 | B381: bogokj.com | C381: 17 | D381: 29 | E381: =SUM(C381,D381)/2 -> 23 | F381: 16 | G381: 25 | H381: =SUM(F381,G381)/2 -> 20.5
A382: 豆瓣读书 | B382: book.douban.com | C382: 427987 | D382: 683667 | E382: =SUM(C382,D382)/2 -> 555827 | F382: 68422 | G382: 91373 | H382: =SUM(F382,G382)/2 -> 79897.5
A383: QQ阅读网 | B383: book.qq.com | C383: 787068 | D383: 1257266 | E383: =SUM(C383,D383)/2 -> 1022167 | F383: 106016 | G383: 153695 | H383: =SUM(F383,G383)/2 -> 129855.5
A384: 文档投稿赚钱 | B384: book118.com | C384: 462051 | D384: 738083 | E384: =SUM(C384,D384)/2 -> 600067 | F384: 328233 | G384: 458800 | H384: =SUM(F384,G384)/2 -> 393516.5
A385: 缤客网 | B385: booking.com | C385: 42888 | D385: 68508 | E385: =SUM(C385,D385)/2 -> 55698 | F385: 14175 | G385: 20366 | H385: =SUM(F385,G385)/2 -> 17270.5
A386: 快眼小说搜索网 | B386: booksky.cc | C386: 3584 | D386: 5724 | E386: =SUM(C386,D386)/2 -> 4654 | F386: 2981 | G386: 4322 | H386: =SUM(F386,G386)/2 -> 3651.5
... A663: 丁丁网 | B663: ddmap.com | C663: 23481 | D663: 37510 | E663: =SUM(C663,D663)/2 -> 30495.5 | F663: 8568 | G663: 16407 | H663: =SUM(F663,G663)/2 -> 12487.5
A664: 多多软件站 | B664: ddooo.com | E664: =SUM(C664,D664)/2 -> 0 | F664: 134333 | G664: 252167 | H664: =SUM(F664,G664)/2 -> 193250
A665: 小红书号购买渠道 | B665: ddphp.cn | C665: 0 | D665: 0 | E665: =SUM(C665,D665)/2 -> 0 | F665: 0 | G665: 0 | H665: =SUM(F665,G665)/2 -> 0
A666: 织梦吧 | B666: dedecms8.com | C666: 4 | D666: 6 | E666: =SUM(C666,D666)/2 -> 5 | F666: 6 | G666: 10 | H666: =SUM(F666,G666)/2 -> 8
A667: DeepModeling | B667: deepmodeling.com | C667: 8 | D667: 12 | E667: =SUM(C667,D667)/2 -> 10 | F667: 2 | G667: 2 | H667: =SUM(F667,G667)/2 -> 2
A668: 北京深度视觉科技 | B668: deepvision-tech.com | C668: 60 | D668: 94 | E668: =SUM(C668,D668)/2 -> 77 | F668: 26 | G668: 38 | H668: =SUM(F668,G668)/2 -> 32
A669: 浙江德励石科技 | B669: delistech.com | C669: 45 | D669: 73 | E669: =SUM(C669,D669)/2 -> 59 | F669: 1 | G669: 1 | H669: =SUM(F669,G669)/2 -> 1
A670: Dell | B670: dell.com | C670: 66403 | D670: 106073 | E670: =SUM(C670,D670)/2 -> 86238 | F670: 16534 | G670: 22378 | H670: =SUM(F670,G670)/2 -> 19456
A671: 德邦物流 | B671: deppon.com | C671: 45407 | D671: 72531 | E671: =SUM(C671,D671)/2 -> 58969 | F671: 10294 | G671: 13660 | H671: =SUM(F671,G671)/2 -> 11977
A672: ZOL桌面壁纸 | B672: desk.zol.com.cn | C672: 43577 | D672: 69610 | E672: =SUM(C672,D672)/2 -> 56593.5 | F672: 5260 | G672: 6331 | H672: =SUM(F672,G672)/2 -> 5795.5
A673: 元桌多开浏览器 | B673: desktxp.cn | C673: 1 | D673: 1 | E673: =SUM(C673,D673)/2 -> 1 | F673: 0 | G673: 0 | H673: =SUM(F673,G673)/2 -> 0
A674: 中关村产品报价 | B674: detail.zol.com.cn | C674: 798078 | D674: 1274850 | E674: =SUM(C674,D674)/2 -> 1036464 | F674: 186937 | G674: 257881 | H674: =SUM(F674,G674)/2 -> 222409
A675: Devart中文官方网站 | B675: devart.com.cn | C675: 0 | D675: 0 | E675: =SUM(C675,D675)/2 -> 0 | F675: 0 | G675: 0 | H675: =SUM(F675,G675)/2 -> 0
A676: 51CTO开发频道 | B676: developer.51cto.com | C676: 122 | D676: 196 | E676: =SUM(C676,D676)/2 -> 159 | F676: 5 | G676: 7 | H676: =SUM(F676,G676)/2 -> 6
A677: 百度开放云平台 | B677: developer.baidu.com | E677: =SUM(C677,D677)/2 -> 0 | F677: 9954 | G677: 13959 | H677: =SUM(F677,G677)/2 -> 11956.5
A678: 大众点评开发者平台 | B678: developer.dianping.com | C678: 23 | D678: 37 | E678: =SUM(C678,D678)/2 -> 30 | F678: 49 | G678: 54 | H678: =SUM(F678,G678)/2 -> 51.5
A679: 华为开发者联盟 | B679: developer.huawei.com | C679: 37401 | D679: 59745 | E679: =SUM(C679,D679)/2 -> 48573 | F679: 3525 | G679: 5738 | H679: =SUM(F679,G679)/2 -> 4631.5
A680: 魅族开发者中心 | B680: developer.meizu.com | C680: 44 | D680: 70 | E680: =SUM(C680,D680)/2 -> 57 | F680: 9 | G680: 14 | H680: =SUM(F680,G680)/2 -> 11.5
A681: 上海软件定制开发 | B681: develop-erp.cn | C681: 6 | D681: 10 | E681: =SUM(C681,D681)/2 -> 8 | F681: 18 | G681: 23 | H681: =SUM(F681,G681)/2 -> 20.5
A682: Google Developers中国网 | B682: developers.google.cn | C682: 18106 | D682: 28920 | E682: =SUM(C682,D682)/2 -> 23513 | H682: =SUM(F682,G682)/2 -> 0
A683: 北京德威特官网 | B683: devot.com | C683: 2 | D683: 4 | E683: =SUM(C683,D683)/2 -> 3 | F683: 1 | G683: 1 | H683: =SUM(F683,G683)/2 -> 1
A684: 思维立方大风车软件 | B684: dfcsoft.com | C684: 11 | D684: 15 | E684: =SUM(C684,D684)/2 -> 13 | F684: 5 | G684: 8 | H684: =SUM(F684,G684)/2 -> 6.5
A685: 东风乘用车公司 | B685: dfpv.com.cn | C685: 10306 | D685: 16462 | E685: =SUM(C685,D685)/2 -> 13384 | F685: 16555 | G685: 24056 | H685: =SUM(F685,G685)/2 -> 20305.5
A686: 中国东莞政府门户网站 | B686: dg.gov.cn | C686: 59285 | D686: 94702 | E686: =SUM(C686,D686)/2 -> 76993.5 | F686: 15494 | G686: 24989 | H686: =SUM(F686,G686)/2 -> 20241.5
A687: 东莞市云触智能科技 | B687: dgctit.com | C687: 2 | D687: 2 | E687: =SUM(C687,D687)/2 -> 2 | F687: 0 | G687: 0 | H687: =SUM(F687,G687)/2 -> 0
A688: 期货直播间 | B688: dgtanshua.com | C688: 33 | D688: 53 | E688: =SUM(C688,D688)/2 -> 43 | F688: 15 | G688: 21 | H688: =SUM(F688,G688)/2 -> 18
A689: DHL网站 | B689: dhl.com | C689: 30297 | D689: 48397 | E689: =SUM(C689,D689)/2 -> 39347 | F689: 6282 | G689: 8077 | H689: =SUM(F689,G689)/2 -> 7179.5
A690: 江苏东华测试技术 | B690: dhtopology.com | C690: 57 | D690: 91 | E690: =SUM(C690,D690)/2 -> 74 | F690: 4 | G690: 20 | H690: =SUM(F690,G690)/2 -> 12
A691: 店查查 | B691: dianchacha.com | C691: 8193 | D691: 13087 | E691: =SUM(C691,D691)/2 -> 10640 | F691: 11782 | G691: 16527 | H691: =SUM(F691,G691)/2 -> 14154.5
A692: 图吧电话查询 | B692: dianhua.mapbar.com | C692: 13885 | D692: 22180 | E692: =SUM(C692,D692)/2 -> 18032.5 | F692: 17457 | G692: 26216 | H692: =SUM(F692,G692)/2 -> 21836.5
A693: 大众点评网 | B693: dianping.com | C693: 267968 | D693: 428056 | E693: =SUM(C693,D693)/2 -> 348012 | F693: 98296 | G693: 137414 | H693: =SUM(F693,G693)/2 -> 117855
...

Sheet 开发者600
A1: 网站名称 | B1: URL | C1: 综合流量 | D1: 开发者600排名
A2: 百度 | B2: baidu.com | C2: 296716943 | D2: 1
A3: 知乎 | B3: zhihu.com | C3: 16451772 | D3: 2
A4: 腾讯网 | B4: qq.com | C4: 12655436 | D4: 3
A5: 哔哩哔哩弹幕视频网 | B5: bilibili.com | C5: 10739342 | D5: 4
A6: 搜狐 | B6: sohu.com | C6: 10530398 | D6: 5
A7: 百度贴吧 | B7: tieba.baidu.com | C7: 10193446 | D7: 6
A8: 网易网 | B8: 163.com | C8: 7681633.9 | D8: 7
A9: 好搜 | B9: so.com | C9: 6986574.3 | D9: 8
A10: 百度图片 | B10: image.baidu.com | C10: 6395387 | D10: 9
A11: 百度文库 | B11: wenku.baidu.com | C11: 5057968 | D11: 10
A12: 微博 | B12: weibo.com | C12: 3386782.2 | D12: 11
A13: 百度地图 | B13: map.baidu.com | C13: 3018368 | D13: 12
... A599: 百度云OS | B599: os.baidu.com | C599: 0 | D599: 598

Sheet 开发者600原始
B1: 网站名称 | C1: URL | D1: 全网流量左 | E1: 全网流量右 | F1: 站长之家平均流量 | G1: 百度来路左 | H1: 百度来路右 | I1: 爱站平均流量 | J1: 综合流量 | K1: 开发者600排名 | L1: 综合排名
A2: 255 | B2: 百度 | C2: baidu.com | D2: {=INDEX('原始数据'!C$2:C$3689,MATCH($C2,'原始数据'!$B$2:$B$3689,0))} -> 0 | E2: {=INDEX('原始数据'!D$2:D$3689,MATCH($C2,'原始数据'!$B$2:$B$3689,0))} -> 0 | F2: {=INDEX('原始数据'!E$2:E$3689,MATCH($C2,'原始数据'!$B$2:$B$3689,0))} -> 0 | G2: {=INDEX('原始数据'!F$2:F$3689,MATCH($C2,'原始数据'!$B$2:$B$3689,0))} -> 119665456 | H2: {=INDEX('原始数据'!G$2:G$3689,MATCH($C2,'原始数据'!$B$2:$B$3689,0))} -> 177051487 | I2: {=INDEX('原始数据'!H$2:H$3689,MATCH($C2,'原始数据'!$B$2:$B$3689,0))} -> 1.4835847e+08 | J2: =IF(F2=0,I2*2,F2/$N$603+I2) -> 296716943 | K2: =ROW(K2)-1 -> 1 | L2: {=INDEX(TOP3277!#REF!,MATCH(C2,TOP3277!$B$501:$B$3035,0))} -> 1
A3: 331 | B3: 百度百科 | C3: baike.baidu.com | D3: {=INDEX('原始数据'!C$2:C$3689,MATCH($C3,'原始数据'!$B$2:$B$3689,0))} -> 0 | E3: {=INDEX('原始数据'!D$2:D$3689,MATCH($C3,'原始数据'!$B$2:$B$3689,0))} -> 0 | F3: {=INDEX('原始数据'!E$2:E$3689,MATCH($C3,'原始数据'!$B$2:$B$3689,0))} -> 0 | G3: {=INDEX('原始数据'!F$2:F$3689,MATCH($C3,'原始数据'!$B$2:$B$3689,0))} -> 27483221 | H3: {=INDEX('原始数据'!G$2:G$3689,MATCH($C3,'原始数据'!$B$2:$B$3689,0))} -> 32825411 | I3: {=INDEX('原始数据'!H$2:H$3689,MATCH($C3,'原始数据'!$B$2:$B$3689,0))} -> 30154316 | J3: =IF(F3=0,I3*2,F3/$N$603+I3) -> 60308632 | K3: =ROW(K3)-1 -> 2 | L3: {=INDEX(TOP3277!#REF!,MATCH(C3,TOP3277!$B$501:$B$3035,0))} -> 2
A4: 335 | B4: 百度知道 | C4: zhidao.baidu.com | F4: =SUM(D4+E4)/2 -> 0 | G4: 10027430 | H4: 15150163 | I4: =SUM(G4+H4)/2 -> 12588796 | J4: =IF(F4=0,I4*2,F4/$N$603+I4) -> 25177593 | K4: =ROW(K4)-1 -> 3 | L4: {=INDEX(TOP3277!#REF!,MATCH(C4,TOP3277!$B$501:$B$3035,0))} -> #N/A
A5: 268 | B5: 百度翻译 | C5: fanyi.baidu.com | F5: =SUM(D5+E5)/2 -> 0 | G5: 11178249 | H5: 12547041 | I5: =SUM(G5+H5)/2 -> 11862645 | J5: =IF(F5=0,I5*2,F5/$N$603+I5) -> 23725290 | K5: =ROW(K5)-1 -> 4 | L5: {=INDEX(TOP3277!#REF!,MATCH(C5,TOP3277!$B$501:$B$3035,0))} -> #N/A
A6: 264 | B6: 知乎 | C6: zhihu.com | D6: {=INDEX('原始数据'!C$2:C$3689,MATCH($C6,'原始数据'!$B$2:$B$3689,0))} -> 48517487 | E6: {=INDEX('原始数据'!D$2:D$3689,MATCH($C6,'原始数据'!$B$2:$B$3689,0))} -> 77501959 | F6: {=INDEX('原始数据'!E$2:E$3689,MATCH($C6,'原始数据'!$B$2:$B$3689,0))} -> 63009723 | G6: {=INDEX('原始数据'!F$2:F$3689,MATCH($C6,'原始数据'!$B$2:$B$3689,0))} -> 4251443 | H6: {=INDEX('原始数据'!G$2:G$3689,MATCH($C6,'原始数据'!$B$2:$B$3689,0))} -> 6013991 | I6: {=INDEX('原始数据'!H$2:H$3689,MATCH($C6,'原始数据'!$B$2:$B$3689,0))} -> 5132717 | J6: =IF(F6=0,I6*2,F6/$N$603+I6) -> 16451772 | K6: =ROW(K6)-1 -> 5 | L6: {=INDEX(TOP3277!#REF!,MATCH(C6,TOP3277!$B$501:$B$3035,0))} -> 4
A7: 256 | B7: 腾讯网 | C7: qq.com | D7: {=INDEX('原始数据'!C$2:C$3689,MATCH($C7,'原始数据'!$B$2:$B$3689,0))} -> 24644366 | E7: {=INDEX('原始数据'!D$2:D$3689,MATCH($C7,'原始数据'!$B$2:$B$3689,0))} -> 39366974 | F7: {=INDEX('原始数据'!E$2:E$3689,MATCH($C7,'原始数据'!$B$2:$B$3689,0))} -> 32005670 | G7: {=INDEX('原始数据'!F$2:F$3689,MATCH($C7,'原始数据'!$B$2:$B$3689,0))} -> 5875170 | H7: {=INDEX('原始数据'!G$2:G$3689,MATCH($C7,'原始数据'!$B$2:$B$3689,0))} -> 7936716 | I7: {=INDEX('原始数据'!H$2:H$3689,MATCH($C7,'原始数据'!$B$2:$B$3689,0))} -> 6905943 | J7: =IF(F7=0,I7*2,F7/$N$603+I7) -> 12655436 | K7: =ROW(K7)-1 -> 6 | L7: {=INDEX(TOP3277!#REF!,MATCH(C7,TOP3277!$B$501:$B$3035,0))} -> 5
A8: 261 | B8: 哔哩哔哩弹幕视频网 | C8: bilibili.com | D8: 12367232 | E8: 19755448 | F8: =SUM(D8+E8)/2 -> 16061340 | G8: 6536051 | H8: 9172120 | I8: =SUM(G8+H8)/2 -> 7854085.5 | J8: =IF(F8=0,I8*2,F8/$N$603+I8) -> 10739342 | K8: =ROW(K8)-1 -> 7 | L8: {=INDEX(TOP3277!#REF!,MATCH(C8,TOP3277!$B$501:$B$3035,0))} -> 8
A9: 257 | B9: 搜狐 | C9: sohu.com | D9: {=INDEX('原始数据'!C$2:C$3689,MATCH($C9,'原始数据'!$B$2:$B$3689,0))} -> 20313897 | E9: {=INDEX('原始数据'!D$2:D$3689,MATCH($C9,'原始数据'!$B$2:$B$3689,0))} -> 32449471 | F9: {=INDEX('原始数据'!E$2:E$3689,MATCH($C9,'原始数据'!$B$2:$B$3689,0))} -> 26381684 | G9: {=INDEX('原始数据'!F$2:F$3689,MATCH($C9,'原始数据'!$B$2:$B$3689,0))} -> 5056295 | H9: {=INDEX('原始数据'!G$2:G$3689,MATCH($C9,'原始数据'!$B$2:$B$3689,0))} -> 6526100 | I9: {=INDEX('原始数据'!H$2:H$3689,MATCH($C9,'原始数据'!$B$2:$B$3689,0))} -> 5791197.5 | J9: =IF(F9=0,I9*2,F9/$N$603+I9) -> 10530398 | K9: =ROW(K9)-1 -> 8 | L9: {=INDEX(TOP3277!#REF!,MATCH(C9,TOP3277!$B$501:$B$3035,0))} -> 6
A10: 330 | B10: 百度贴吧 | C10: tieba.baidu.com | D10: {=INDEX('原始数据'!C$2:C$3689,MATCH($C10,'原始数据'!$B$2:$B$3689,0))} -> 0 | E10: {=INDEX('原始数据'!D$2:D$3689,MATCH($C10,'原始数据'!$B$2:$B$3689,0))} -> 0 | F10: {=INDEX('原始数据'!E$2:E$3689,MATCH($C10,'原始数据'!$B$2:$B$3689,0))} -> 0 | G10: {=INDEX('原始数据'!F$2:F$3689,MATCH($C10,'原始数据'!$B$2:$B$3689,0))} -> 4305895 | H10: {=INDEX('原始数据'!G$2:G$3689,MATCH($C10,'原始数据'!$B$2:$B$3689,0))} -> 5887551 | I10: {=INDEX('原始数据'!H$2:H$3689,MATCH($C10,'原始数据'!$B$2:$B$3689,0))} -> 5096723 | J10: =IF(F10=0,I10*2,F10/$N$603+I10) -> 10193446 | K10: =ROW(K10)-1 -> 9 | L10: {=INDEX(TOP3277!#REF!,MATCH(C10,TOP3277!$B$501:$B$3035,0))} -> 7
A11: 13 | B11: 网易网 | C11: 163.com | D11: {=INDEX('原始数据'!C$2:C$3689,MATCH($C11,'原始数据'!$B$2:$B$3689,0))} -> 10588890 | E11: {=INDEX('原始数据'!D$2:D$3689,MATCH($C11,'原始数据'!$B$2:$B$3689,0))} -> 16914722 | F11: {=INDEX('原始数据'!E$2:E$3689,MATCH($C11,'原始数据'!$B$2:$B$3689,0))} -> 13751806 | G11: {=INDEX('原始数据'!F$2:F$3689,MATCH($C11,'原始数据'!$B$2:$B$3689,0))} -> 3513687 | H11: {=INDEX('原始数据'!G$2:G$3689,MATCH($C11,'原始数据'!$B$2:$B$3689,0))} -> 6908837 | I11: {=INDEX('原始数据'!H$2:H$3689,MATCH($C11,'原始数据'!$B$2:$B$3689,0))} -> 5211262 | J11: =IF(F11=0,I11*2,F11/$N$603+I11) -> 7681633.9 | K11: =ROW(K11)-1 -> 10 | L11: {=INDEX(TOP3277!#REF!,MATCH(C11,TOP3277!$B$501:$B$3035,0))} -> 9
A12: 259 | B12: 好搜 | C12: so.com | D12: {=INDEX('原始数据'!C$2:C$3689,MATCH($C12,'原始数据'!$B$2:$B$3689,0))} -> 25568836 | E12: {=INDEX('原始数据'!D$2:D$3689,MATCH($C12,'原始数据'!$B$2:$B$3689,0))} -> 40843726 | F12: {=INDEX('原始数据'!E$2:E$3689,MATCH($C12,'原始数据'!$B$2:$B$3689,0))} -> 33206281 | G12: {=INDEX('原始数据'!F$2:F$3689,MATCH($C12,'原始数据'!$B$2:$B$3689,0))} -> 759504 | H12: {=INDEX('原始数据'!G$2:G$3689,MATCH($C12,'原始数据'!$B$2:$B$3689,0))} -> 1283304 | I12: {=INDEX('原始数据'!H$2:H$3689,MATCH($C12,'原始数据'!$B$2:$B$3689,0))} -> 1021404 | J12: =IF(F12=0,I12*2,F12/$N$603+I12) -> 6986574.3 | K12: =ROW(K12)-1 -> 11 | L12: {=INDEX(TOP3277!#REF!,MATCH(C12,TOP3277!$B$501:$B$3035,0))} -> 10
A13: 332 | B13: 百度图片 | C13: image.baidu.com | F13: =SUM(D13+E13)/2 -> 0 | G13: 2795541 | H13: 3599846 | I13: =SUM(G13+H13)/2 -> 3197693.5 | J13: =IF(F13=0,I13*2,F13/$N$603+I13) -> 6395387 | K13: =ROW(K13)-1 -> 12 | L13: {=INDEX(TOP3277!#REF!,MATCH(C13,TOP3277!$B$501:$B$3035,0))} -> #N/A
A14: 333 | B14: 百度文库 | C14: wenku.baidu.com | D14: {=INDEX('原始数据'!C$2:C$3689,MATCH($C14,'原始数据'!$B$2:$B$3689,0))} -> 0 | E14: {=INDEX('原始数据'!D$2:D$3689,MATCH($C14,'原始数据'!$B$2:$B$3689,0))} -> 0 | F14: {=INDEX('原始数据'!E$2:E$3689,MATCH($C14,'原始数据'!$B$2:$B$3689,0))} -> 0 | G14: {=INDEX('原始数据'!F$2:F$3689,MATCH($C14,'原始数据'!$B$2:$B$3689,0))} -> 2226174 | H14: {=INDEX('原始数据'!G$2:G$3689,MATCH($C14,'原始数据'!$B$2:$B$3689,0))} -> 2831794 | I14: {=INDEX('原始数据'!H$2:H$3689,MATCH($C14,'原始数据'!$B$2:$B$3689,0))} -> 2528984 | J14: =IF(F14=0,I14*2,F14/$N$603+I14) -> 5057968 | K14: =ROW(K14)-1 -> 13 | L14: {=INDEX(TOP3277!#REF!,MATCH(C14,TOP3277!$B$501:$B$3035,0))} -> 14
A15: 201 | B15: 微博 | C15: weibo.com | D15: {=INDEX('原始数据'!C$2:C$3689,MATCH($C15,'原始数据'!$B$2:$B$3689,0))} -> 5615978 | E15: {=INDEX('原始数据'!D$2:D$3689,MATCH($C15,'原始数据'!$B$2:$B$3689,0))} -> 8970979 | F15: {=INDEX('原始数据'!E$2:E$3689,MATCH($C15,'原始数据'!$B$2:$B$3689,0))} -> 7293478.5 | G15: {=INDEX('原始数据'!F$2:F$3689,MATCH($C15,'原始数据'!$B$2:$B$3689,0))} -> 1664072 | H15: {=INDEX('原始数据'!G$2:G$3689,MATCH($C15,'原始数据'!$B$2:$B$3689,0))} -> 2489094 | I15: {=INDEX('原始数据'!H$2:H$3689,MATCH($C15,'原始数据'!$B$2:$B$3689,0))} -> 2076583 | J15: =IF(F15=0,I15*2,F15/$N$603+I15) -> 3386782.2 | K15: =ROW(K15)-1 -> 14 | L15: {=INDEX(TOP3277!#REF!,MATCH(C15,TOP3277!$B$501:$B$3035,0))} -> 17
A16: 338 | B16: 百度地图 | C16: map.baidu.com | F16: =SUM(D16+E16)/2 -> 0 | G16: 1365205 | H16: 1653163 | I16: =SUM(G16+H16)/2 -> 1509184 | J16: =IF(F16=0,I16*2,F16/$N$603+I16) -> 3018368 | K16: =ROW(K16)-1 -> 15 | L16: {=INDEX(TOP3277!#REF!,MATCH(C16,TOP3277!$B$501:$B$3035,0))} -> #N/A
A17: 258 | B17: 新浪网 | C17: sina.com.cn | D17: {=INDEX('原始数据'!C$2:C$3689,MATCH($C17,'原始数据'!$B$2:$B$3689,0))} -> 5237766 | E17: {=INDEX('原始数据'!D$2:D$3689,MATCH($C17,'原始数据'!$B$2:$B$3689,0))} -> 8366818 | F17: {=INDEX('原始数据'!E$2:E$3689,MATCH($C17,'原始数据'!$B$2:$B$3689,0))} -> 6802292 | G17: {=INDEX('原始数据'!F$2:F$3689,MATCH($C17,'原始数据'!$B$2:$B$3689,0))} -> 1354640 | H17: {=INDEX('原始数据'!G$2:G$3689,MATCH($C17,'原始数据'!$B$2:$B$3689,0))} -> 1895503 | I17: {=INDEX('原始数据'!H$2:H$3689,MATCH($C17,'原始数据'!$B$2:$B$3689,0))} -> 1625071.5 | J17: =IF(F17=0,I17*2,F17/$N$603+I17) -> 2847034 | K17: =ROW(K17)-1 -> 16 | L17: {=INDEX(TOP3277!#REF!,MATCH(C17,TOP3277!$B$501:$B$3035,0))} -> 21
A18: 260 | B18: 搜狗 | C18: sogou.com | D18: {=INDEX('原始数据'!C$2:C$3689,MATCH($C18,'原始数据'!$B$2:$B$3689,0))} -> 10447085 | E18: {=INDEX('原始数据'!D$2:D$3689,MATCH($C18,'原始数据'!$B$2:$B$3689,0))} -> 16688201 | F18: {=INDEX('原始数据'!E$2:E$3689,MATCH($C18,'原始数据'!$B$2:$B$3689,0))} -> 13567643 | G18: {=INDEX('原始数据'!F$2:F$3689,MATCH($C18,'原始数据'!$B$2:$B$3689,0))} -> 223668 | H18: {=INDEX('原始数据'!G$2:G$3689,MATCH($C18,'原始数据'!$B$2:$B$3689,0))} -> 318745 | I18: {=INDEX('原始数据'!H$2:H$3689,MATCH($C18,'原始数据'!$B$2:$B$3689,0))} -> 271206.5 | J18: =IF(F18=0,I18*2,F18/$N$603+I18) -> 2708495.4 | K18: =ROW(K18)-1 -> 17 | L18: {=INDEX(TOP3277!#REF!,MATCH(C18,TOP3277!$B$501:$B$3035,0))} -> 19
A19: 267 | B19: 优酷网 | C19: youku.com | D19: {=INDEX('原始数据'!C$2:C$3689,MATCH($C19,'原始数据'!$B$2:$B$3689,0))} -> 3712087 | E19: {=INDEX('原始数据'!D$2:D$3689,MATCH($C19,'原始数据'!$B$2:$B$3689,0))} -> 5929697 | F19: {=INDEX('原始数据'!E$2:E$3689,MATCH($C19,'原始数据'!$B$2:$B$3689,0))} -> 4820892 | G19: {=INDEX('原始数据'!F$2:F$3689,MATCH($C19,'原始数据'!$B$2:$B$3689,0))} -> 1106643 | H19: {=INDEX('原始数据'!G$2:G$3689,MATCH($C19,'原始数据'!$B$2:$B$3689,0))} -> 1605421 | I19: {=INDEX('原始数据'!H$2:H$3689,MATCH($C19,'原始数据'!$B$2:$B$3689,0))} -> 1356032 | J19: =IF(F19=0,I19*2,F19/$N$603+I19) -> 2222056.2 | K19: =ROW(K19)-1 -> 18 | L19: {=INDEX(TOP3277!#REF!,MATCH(C19,TOP3277!$B$501:$B$3035,0))} -> 24
A20: 263 | B20: 爱奇艺 | C20: iqiyi.com | D20: {=INDEX('原始数据'!C$2:C$3689,MATCH($C20,'原始数据'!$B$2:$B$3689,0))} -> 3648432 | E20: {=INDEX('原始数据'!D$2:D$3689,MATCH($C20,'原始数据'!$B$2:$B$3689,0))} -> 5828016 | F20: {=INDEX('原始数据'!E$2:E$3689,MATCH($C20,'原始数据'!$B$2:$B$3689,0))} -> 4738224 | G20: {=INDEX('原始数据'!F$2:F$3689,MATCH($C20,'原始数据'!$B$2:$B$3689,0))} -> 1117228 | H20: {=INDEX('原始数据'!G$2:G$3689,MATCH($C20,'原始数据'!$B$2:$B$3689,0))} -> 1588080 | I20: {=INDEX('原始数据'!H$2:H$3689,MATCH($C20,'原始数据'!$B$2:$B$3689,0))} -> 1352654 | J20: =IF(F20=0,I20*2,F20/$N$603+I20) -> 2203827.7 | K20: =ROW(K20)-1 -> 19 | L20: {=INDEX(TOP3277!#REF!,MATCH(C20,TOP3277!$B$501:$B$3035,0))} -> 25
A21: 27 | B21: 中关村在线 | C21: zol.com.cn | D21: {=INDEX('原始数据'!C$2:C$3689,MATCH($C21,'原始数据'!$B$2:$B$3689,0))} -> 2439370 | E21: {=INDEX('原始数据'!D$2:D$3689,MATCH($C21,'原始数据'!$B$2:$B$3689,0))} -> 3896658 | F21: {=INDEX('原始数据'!E$2:E$3689,MATCH($C21,'原始数据'!$B$2:$B$3689,0))} -> 3168014 | G21: {=INDEX('原始数据'!F$2:F$3689,MATCH($C21,'原始数据'!$B$2:$B$3689,0))} -> 1197520 | H21: {=INDEX('原始数据'!G$2:G$3689,MATCH($C21,'原始数据'!$B$2:$B$3689,0))} -> 1741906 | I21: {=INDEX('原始数据'!H$2:H$3689,MATCH($C21,'原始数据'!$B$2:$B$3689,0))} -> 1469713 | J21: =IF(F21=0,I21*2,F21/$N$603+I21) -> 2038814.5 | K21: =ROW(K21)-1 -> 20 | L21: {=INDEX(TOP3277!#REF!,MATCH(C21,TOP3277!$B$501:$B$3035,0))} -> 28
A22: 334 | B22: 百度经验 | C22: jingyan.baidu.com | F22: =SUM(D22+E22)/2 -> 0 | G22: 818986 | H22: 1058383 | I22: =SUM(G22+H22)/2 -> 938684.5 | J22: =IF(F22=0,I22*2,F22/$N$603+I22) -> 1877369 | K22: =ROW(K22)-1 -> 21 | L22: {=INDEX(TOP3277!#REF!,MATCH(C22,TOP3277!$B$501:$B$3035,0))} -> #N/A
A23: 45 | B23: CSDN社区 | C23: csdn.net | D23: {=INDEX('原始数据'!C$2:C$3689,MATCH($C23,'原始数据'!$B$2:$B$3689,0))} -> 4039682 | E23: {=INDEX('原始数据'!D$2:D$3689,MATCH($C23,'原始数据'!$B$2:$B$3689,0))} -> 6452998 | F23: {=INDEX('原始数据'!E$2:E$3689,MATCH($C23,'原始数据'!$B$2:$B$3689,0))} -> 5246340 | G23: {=INDEX('原始数据'!F$2:F$3689,MATCH($C23,'原始数据'!$B$2:$B$3689,0))} -> 672050 | H23: {=INDEX('原始数据'!G$2:G$3689,MATCH($C23,'原始数据'!$B$2:$B$3689,0))} -> 1008281 | I23: {=INDEX('原始数据'!H$2:H$3689,MATCH($C23,'原始数据'!$B$2:$B$3689,0))} -> 840165.5 | J23: =IF(F23=0,I23*2,F23/$N$603+I23) -> 1782617.1 | K23: =ROW(K23)-1 -> 22 | L23: {=INDEX(TOP3277!#REF!,MATCH(C23,TOP3277!$B$501:$B$3035,0))} -> 29
A24: 262 | B24: 京东商城 | C24: jd.com | D24: {=INDEX('原始数据'!C$2:C$3689,MATCH($C24,'原始数据'!$B$2:$B$3689,0))} -> 2490481 | E24: {=INDEX('原始数据'!D$2:D$3689,MATCH($C24,'原始数据'!$B$2:$B$3689,0))} -> 3978298 | F24: {=INDEX('原始数据'!E$2:E$3689,MATCH($C24,'原始数据'!$B$2:$B$3689,0))} -> 3234389.5 | G24: {=INDEX('原始数据'!F$2:F$3689,MATCH($C24,'原始数据'!$B$2:$B$3689,0))} -> 474227 | H24: {=INDEX('原始数据'!G$2:G$3689,MATCH($C24,'原始数据'!$B$2:$B$3689,0))} -> 693151 | I24: {=INDEX('原始数据'!H$2:H$3689,MATCH($C24,'原始数据'!$B$2:$B$3689,0))} -> 583689 | J24: =IF(F24=0,I24*2,F24/$N$603+I24) -> 1164714.1 | K24: =ROW(K24)-1 -> 23 | L24: {=INDEX(TOP3277!#REF!,MATCH(C24,TOP3277!$B$501:$B$3035,0))} -> 47
A25: 56 | B25: 太平洋电脑网 | C25: pconline.com.cn | D25: {=INDEX('原始数据'!C$2:C$3689,MATCH($C25,'原始数据'!$B$2:$B$3689,0))} -> 1270511 | E25: {=INDEX('原始数据'!D$2:D$3689,MATCH($C25,'原始数据'!$B$2:$B$3689,0))} -> 2029517 | F25: {=INDEX('原始数据'!E$2:E$3689,MATCH($C25,'原始数据'!$B$2:$B$3689,0))} -> 1650014 | G25: {=INDEX('原始数据'!F$2:F$3689,MATCH($C25,'原始数据'!$B$2:$B$3689,0))} -> 542177 | H25: {=INDEX('原始数据'!G$2:G$3689,MATCH($C25,'原始数据'!$B$2:$B$3689,0))} -> 765275 | I25: {=INDEX('原始数据'!H$2:H$3689,MATCH($C25,'原始数据'!$B$2:$B$3689,0))} -> 653726 | J25: =IF(F25=0,I25*2,F25/$N$603+I25) -> 950134.22 | K25: =ROW(K25)-1 -> 24 | L25: {=INDEX(TOP3277!#REF!,MATCH(C25,TOP3277!$B$501:$B$3035,0))} -> 60
A26: 177 | B26: 360安全中心 | C26: 360.cn | D26: {=INDEX('原始数据'!C$2:C$3689,MATCH($C26,'原始数据'!$B$2:$B$3689,0))} -> 3190060 | E26: {=INDEX('原始数据'!D$2:D$3689,MATCH($C26,'原始数据'!$B$2:$B$3689,0))} -> 5095812 | F26: {=INDEX('原始数据'!E$2:E$3689,MATCH($C26,'原始数据'!$B$2:$B$3689,0))} -> 4142936 | G26: {=INDEX('原始数据'!F$2:F$3689,MATCH($C26,'原始数据'!$B$2:$B$3689,0))} -> 158977 | H26: {=INDEX('原始数据'!G$2:G$3689,MATCH($C26,'原始数据'!$B$2:$B$3689,0))} -> 224514 | I26: {=INDEX('原始数据'!H$2:H$3689,MATCH($C26,'原始数据'!$B$2:$B$3689,0))} -> 191745.5 | J26: =IF(F26=0,I26*2,F26/$N$603+I26) -> 935981.77 | K26: =ROW(K26)-1 -> 25 | L26: {=INDEX(TOP3277!#REF!,MATCH(C26,TOP3277!$B$501:$B$3035,0))} -> 59
A27: 269 | B27: 腾讯视频 | C27: v.qq.com | D27: {=INDEX('原始数据'!C$2:C$3689,MATCH($C27,'原始数据'!$B$2:$B$3689,0))} -> 1506113 | E27: {=INDEX('原始数据'!D$2:D$3689,MATCH($C27,'原始数据'!$B$2:$B$3689,0))} -> 2405869 | F27: {=INDEX('原始数据'!E$2:E$3689,MATCH($C27,'原始数据'!$B$2:$B$3689,0))} -> 1955991 | G27: {=INDEX('原始数据'!F$2:F$3689,MATCH($C27,'原始数据'!$B$2:$B$3689,0))} -> 244241 | H27: {=INDEX('原始数据'!G$2:G$3689,MATCH($C27,'原始数据'!$B$2:$B$3689,0))} -> 326689 | I27: {=INDEX('原始数据'!H$2:H$3689,MATCH($C27,'原始数据'!$B$2:$B$3689,0))} -> 285465 | J27: =IF(F27=0,I27*2,F27/$N$603+I27) -> 636838.87 | K27: =ROW(K27)-1 -> 26 | L27: {=INDEX(TOP3277!#REF!,MATCH(C27,TOP3277!$B$501:$B$3035,0))} -> 79
A28: 266 | B28: 站长之家 | C28: chinaz.com | D28: {=INDEX('原始数据'!C$2:C$3689,MATCH($C28,'原始数据'!$B$2:$B$3689,0))} -> 1099934 | E28: {=INDEX('原始数据'!D$2:D$3689,MATCH($C28,'原始数据'!$B$2:$B$3689,0))} -> 1757040 | F28: {=INDEX('原始数据'!E$2:E$3689,MATCH($C28,'原始数据'!$B$2:$B$3689,0))} -> 1428487 | G28: {=INDEX('原始数据'!F$2:F$3689,MATCH($C28,'原始数据'!$B$2:$B$3689,0))} -> 313834 | H28: {=INDEX('原始数据'!G$2:G$3689,MATCH($C28,'原始数据'!$B$2:$B$3689,0))} -> 422381 | I28: {=INDEX('原始数据'!H$2:H$3689,MATCH($C28,'原始数据'!$B$2:$B$3689,0))} -> 368107.5 | J28: =IF(F28=0,I28*2,F28/$N$603+I28) -> 624720.65 | K28: =ROW(K28)-1 -> 27 | L28: {=INDEX(TOP3277!#REF!,MATCH(C28,TOP3277!$B$501:$B$3035,0))} -> 91
A29: 332 | B29: 脚本之家 | C29: jb51.net | D29: {=INDEX('原始数据'!C$2:C$3689,MATCH($C29,'原始数据'!$B$2:$B$3689,0))} -> 785075 | E29: {=INDEX('原始数据'!D$2:D$3689,MATCH($C29,'原始数据'!$B$2:$B$3689,0))} -> 1254083 | F29: {=INDEX('原始数据'!E$2:E$3689,MATCH($C29,'原始数据'!$B$2:$B$3689,0))} -> 1019579 | G29: {=INDEX('原始数据'!F$2:F$3689,MATCH($C29,'原始数据'!$B$2:$B$3689,0))} -> 266015 | H29: {=INDEX('原始数据'!G$2:G$3689,MATCH($C29,'原始数据'!$B$2:$B$3689,0))} -> 415010 | I29: {=INDEX('原始数据'!H$2:H$3689,MATCH($C29,'原始数据'!$B$2:$B$3689,0))} -> 340512.5 | J29: =IF(F29=0,I29*2,F29/$N$603+I29) -> 523669.49 | K29: =ROW(K29)-1 -> 28 | L29: {=INDEX(TOP3277!#REF!,MATCH(C29,TOP3277!$B$501:$B$3035,0))} -> 104
A30: 352 | B30: 百度音乐 | C30: music.baidu.com | F30: =SUM(D30+E30)/2 -> 0 | G30: 195025 | H30: 257305 | I30: =SUM(G30+H30)/2 -> 226165 | J30: =IF(F30=0,I30*2,F30/$N$603+I30) -> 452330 | K30: =ROW(K30)-1 -> 29 | L30: {=INDEX(TOP3277!#REF!,MATCH(C30,TOP3277!$B$501:$B$3035,0))} -> #N/A
A31: 265 | B31: IP地址查询 | C31: ip138.com | D31: 1319047 | E31: 2107051 | F31: =SUM(D31+E31)/2 -> 1713049 | G31: 80532 | H31: 135094 | I31: =SUM(G31+H31)/2 -> 107813 | J31: =IF(F31=0,I31*2,F31/$N$603+I31) -> 415544.81 | K31: =ROW(K31)-1 -> 30 | L31: {=INDEX(TOP3277!#REF!,MATCH(C31,TOP3277!$B$501:$B$3035,0))} -> 229
A32: 324 | B32: 多多软件站 | C32: ddooo.com | D32: {=INDEX('原始数据'!C$2:C$3689,MATCH($C32,'原始数据'!$B$2:$B$3689,0))} -> 0 | E32: {=INDEX('原始数据'!D$2:D$3689,MATCH($C32,'原始数据'!$B$2:$B$3689,0))} -> 0 | F32: {=INDEX('原始数据'!E$2:E$3689,MATCH($C32,'原始数据'!$B$2:$B$3689,0))} -> 0 | G32: {=INDEX('原始数据'!F$2:F$3689,MATCH($C32,'原始数据'!$B$2:$B$3689,0))} -> 134333 | H32: {=INDEX('原始数据'!G$2:G$3689,MATCH($C32,'原始数据'!$B$2:$B$3689,0))} -> 252167 | I32: {=INDEX('原始数据'!H$2:H$3689,MATCH($C32,'原始数据'!$B$2:$B$3689,0))} -> 193250 | J32: =IF(F32=0,I32*2,F32/$N$603+I32) -> 386500 | K32: =ROW(K32)-1 -> 31 | L32: {=INDEX(TOP3277!#REF!,MATCH(C32,TOP3277!$B$501:$B$3035,0))} -> 142
A33: 187 | B33: 觅知素材网 | C33: 51miz.com | D33: {=INDEX('原始数据'!C$2:C$3689,MATCH($C33,'原始数据'!$B$2:$B$3689,0))} -> 824261 | E33: {=INDEX('原始数据'!D$2:D$3689,MATCH($C33,'原始数据'!$B$2:$B$3689,0))} -> 1316673 | F33: {=INDEX('原始数据'!E$2:E$3689,MATCH($C33,'原始数据'!$B$2:$B$3689,0))} -> 1070467 | G33: {=INDEX('原始数据'!F$2:F$3689,MATCH($C33,'原始数据'!$B$2:$B$3689,0))} -> 155751 | H33: {=INDEX('原始数据'!G$2:G$3689,MATCH($C33,'原始数据'!$B$2:$B$3689,0))} -> 224229 | I33: {=INDEX('原始数据'!H$2:H$3689,MATCH($C33,'原始数据'!$B$2:$B$3689,0))} -> 189990 | J33: =IF(F33=0,I33*2,F33/$N$603+I33) -> 382288.5 | K33: =ROW(K33)-1 -> 32 | L33: {=INDEX(TOP3277!#REF!,MATCH(C33,TOP3277!$B$501:$B$3035,0))} -> 133
A34: 270 | B34: 华为 | C34: huawei.com | D34: {=INDEX('原始数据'!C$2:C$3689,MATCH($C34,'原始数据'!$B$2:$B$3689,0))} -> 659045 | E34: {=INDEX('原始数据'!D$2:D$3689,MATCH($C34,'原始数据'!$B$2:$B$3689,0))} -> 1052763 | F34: {=INDEX('原始数据'!E$2:E$3689,MATCH($C34,'原始数据'!$B$2:$B$3689,0))} -> 855904 | G34: {=INDEX('原始数据'!F$2:F$3689,MATCH($C34,'原始数据'!$B$2:$B$3689,0))} -> 161946 | H34: {=INDEX('原始数据'!G$2:G$3689,MATCH($C34,'原始数据'!$B$2:$B$3689,0))} -> 217036 | I34: {=INDEX('原始数据'!H$2:H$3689,MATCH($C34,'原始数据'!$B$2:$B$3689,0))} -> 189491 | J34: =IF(F34=0,I34*2,F34/$N$603+I34) -> 343245.44 | K34: =ROW(K34)-1 -> 33 | L34: {=INDEX(TOP3277!#REF!,MATCH(C34,TOP3277!$B$501:$B$3035,0))} -> 147
A35: 203 | B35: 博客园 | C35: cnblogs.com | D35: {=INDEX('原始数据'!C$2:C$3689,MATCH($C35,'原始数据'!$B$2:$B$3689,0))} -> 659174 | E35: {=INDEX('原始数据'!D$2:D$3689,MATCH($C35,'原始数据'!$B$2:$B$3689,0))} -> 1052964 | F35: {=INDEX('原始数据'!E$2:E$3689,MATCH($C35,'原始数据'!$B$2:$B$3689,0))} -> 856069 | G35: {=INDEX('原始数据'!F$2:F$3689,MATCH($C35,'原始数据'!$B$2:$B$3689,0))} -> 160533 | H35: {=INDEX('原始数据'!G$2:G$3689,MATCH($C35,'原始数据'!$B$2:$B$3689,0))} -> 204778 | I35: {=INDEX('原始数据'!H$2:H$3689,MATCH($C35,'原始数据'!$B$2:$B$3689,0))} -> 182655.5 | J35: =IF(F35=0,I35*2,F35/$N$603+I35) -> 336439.58 | K35: =ROW(K35)-1 -> 34 | L35: {=INDEX(TOP3277!#REF!,MATCH(C35,TOP3277!$B$501:$B$3035,0))} -> 149
A36: 191 | B36: 天极网 | C36: yesky.com | D36: {=INDEX('原始数据'!C$2:C$3689,MATCH($C36,'原始数据'!$B$2:$B$3689,0))} -> 415205 | E36: {=INDEX('原始数据'!D$2:D$3689,MATCH($C36,'原始数据'!$B$2:$B$3689,0))} -> 663251 | F36: {=INDEX('原始数据'!E$2:E$3689,MATCH($C36,'原始数据'!$B$2:$B$3689,0))} -> 539228 | G36: {=INDEX('原始数据'!F$2:F$3689,MATCH($C36,'原始数据'!$B$2:$B$3689,0))} -> 139294 | H36: {=INDEX('原始数据'!G$2:G$3689,MATCH($C36,'原始数据'!$B$2:$B$3689,0))} -> 201917 | I36: {=INDEX('原始数据'!H$2:H$3689,MATCH($C36,'原始数据'!$B$2:$B$3689,0))} -> 170605.5 | J36: =IF(F36=0,I36*2,F36/$N$603+I36) -> 267472.32 | K36: =ROW(K36)-1 -> 35 | L36: {=INDEX(TOP3277!#REF!,MATCH(C36,TOP3277!$B$501:$B$3035,0))} -> 180
A37: 413 | B37: 当易网 | C37: downyi.com | D37: {=INDEX('原始数据'!C$2:C$3689,MATCH($C37,'原始数据'!$B$2:$B$3689,0))} -> 310438 | E37: {=INDEX('原始数据'!D$2:D$3689,MATCH($C37,'原始数据'!$B$2:$B$3689,0))} -> 495896 | F37: {=INDEX('原始数据'!E$2:E$3689,MATCH($C37,'原始数据'!$B$2:$B$3689,0))} -> 403167 | G37: {=INDEX('原始数据'!F$2:F$3689,MATCH($C37,'原始数据'!$B$2:$B$3689,0))} -> 137714 | H37: {=INDEX('原始数据'!G$2:G$3689,MATCH($C37,'原始数据'!$B$2:$B$3689,0))} -> 202143 | I37: {=INDEX('原始数据'!H$2:H$3689,MATCH($C37,'原始数据'!$B$2:$B$3689,0))} -> 169928.5 | J37: =IF(F37=0,I37*2,F37/$N$603+I37) -> 242353.35 | K37: =ROW(K37)-1 -> 36 | L37: {=INDEX(TOP3277!#REF!,MATCH(C37,TOP3277!$B$501:$B$3035,0))} -> 194
A38: 339 | B38: php中文网 | C38: php.cn | D38: {=INDEX('原始数据'!C$2:C$3689,MATCH($C38,'原始数据'!$B$2:$B$3689,0))} -> 502376 | E38: {=INDEX('原始数据'!D$2:D$3689,MATCH($C38,'原始数据'!$B$2:$B$3689,0))} -> 802496 | F38: {=INDEX('原始数据'!E$2:E$3689,MATCH($C38,'原始数据'!$B$2:$B$3689,0))} -> 652436 | G38: {=INDEX('原始数据'!F$2:F$3689,MATCH($C38,'原始数据'!$B$2:$B$3689,0))} -> 73012 | H38: {=INDEX('原始数据'!G$2:G$3689,MATCH($C38,'原始数据'!$B$2:$B$3689,0))} -> 104658 | I38: {=INDEX('原始数据'!H$2:H$3689,MATCH($C38,'原始数据'!$B$2:$B$3689,0))} -> 88835 | J38: =IF(F38=0,I38*2,F38/$N$603+I38) -> 206038.48 | K38: =ROW(K38)-1 -> 37 | L38: {=INDEX(TOP3277!#REF!,MATCH(C38,TOP3277!$B$501:$B$3035,0))} -> 214
A39: 1267 | B39: 吾爱破解论 | C39: 52pojie.cn | D39: {=INDEX('原始数据'!C$2:C$3689,MATCH($C39,'原始数据'!$B$2:$B$3689,0))} -> 816360 | E39: {=INDEX('原始数据'!D$2:D$3689,MATCH($C39,'原始数据'!$B$2:$B$3689,0))} -> 1304054 | F39: {=INDEX('原始数据'!E$2:E$3689,MATCH($C39,'原始数据'!$B$2:$B$3689,0))} -> 1060207 | G39: {=INDEX('原始数据'!F$2:F$3689,MATCH($C39,'原始数据'!$B$2:$B$3689,0))} -> 8607 | H39: {=INDEX('原始数据'!G$2:G$3689,MATCH($C39,'原始数据'!$B$2:$B$3689,0))} -> 13770 | I39: {=INDEX('原始数据'!H$2:H$3689,MATCH($C39,'原始数据'!$B$2:$B$3689,0))} -> 11188.5 | J39: =IF(F39=0,I39*2,F39/$N$603+I39) -> 201643.89 | K39: =ROW(K39)-1 -> 38 | L39: {=INDEX(TOP3277!#REF!,MATCH(C39,TOP3277!$B$501:$B$3035,0))} -> 203
A40: 274 | B40: IT猫扑网 | C40: itmop.com | D40: {=INDEX('原始数据'!C$2:C$3689,MATCH($C40,'原始数据'!$B$2:$B$3689,0))} -> 179190 | E40: {=INDEX('原始数据'!D$2:D$3689,MATCH($C40,'原始数据'!$B$2:$B$3689,0))} -> 286238 | F40: {=INDEX('原始数据'!E$2:E$3689,MATCH($C40,'原始数据'!$B$2:$B$3689,0))} -> 232714 | G40: {=INDEX('原始数据'!F$2:F$3689,MATCH($C40,'原始数据'!$B$2:$B$3689,0))} -> 123588 | H40: {=INDEX('原始数据'!G$2:G$3689,MATCH($C40,'原始数据'!$B$2:$B$3689,0))} -> 187468 | I40: {=INDEX('原始数据'!H$2:H$3689,MATCH($C40,'原始数据'!$B$2:$B$3689,0))} -> 155528 | J40: =IF(F40=0,I40*2,F40/$N$603+I40) -> 197332.7 | K40: =ROW(K40)-1 -> 39 | L40: {=INDEX(TOP3277!#REF!,MATCH(C40,TOP3277!$B$501:$B$3035,0))} -> 225
A41: 596 | B41: 百度云 | C41: pan.baidu.com | D41: {=INDEX('原始数据'!C$2:C$3689,MATCH($C41,'原始数据'!$B$2:$B$3689,0))} -> 0 | E41: {=INDEX('原始数据'!D$2:D$3689,MATCH($C41,'原始数据'!$B$2:$B$3689,0))} -> 0 | F41: {=INDEX('原始数据'!E$2:E$3689,MATCH($C41,'原始数据'!$B$2:$B$3689,0))} -> 0 | G41: 75323 | H41: 85492 | I41: {=INDEX('原始数据'!H$2:H$3689,MATCH($C41,'原始数据'!$B$2:$B$3689,0))} -> 79963 | J41: =IF(F41=0,I41*2,F41/$N$603+I41) -> 159926 | K41: =ROW(K41)-1 -> 40 | L41: {=INDEX(TOP3277!#REF!,MATCH(C41,TOP3277!$B$501:$B$3035,0))} -> #N/A
A42: 287 | B42: 51CTO | C42: 51cto.com | D42: {=INDEX('原始数据'!C$2:C$3689,MATCH($C42,'原始数据'!$B$2:$B$3689,0))} -> 172264 | E42: {=INDEX('原始数据'!D$2:D$3689,MATCH($C42,'原始数据'!$B$2:$B$3689,0))} -> 275176 | F42: {=INDEX('原始数据'!E$2:E$3689,MATCH($C42,'原始数据'!$B$2:$B$3689,0))} -> 223720 | G42: {=INDEX('原始数据'!F$2:F$3689,MATCH($C42,'原始数据'!$B$2:$B$3689,0))} -> 100970 | H42: {=INDEX('原始数据'!G$2:G$3689,MATCH($C42,'原始数据'!$B$2:$B$3689,0))} -> 138309 | I42: {=INDEX('原始数据'!H$2:H$3689,MATCH($C42,'原始数据'!$B$2:$B$3689,0))} -> 119639.5 | J42: =IF(F42=0,I42*2,F42/$N$603+I42) -> 159828.52 | K42: =ROW(K42)-1 -> 41 | L42: {=INDEX(TOP3277!#REF!,MATCH(C42,TOP3277!$B$501:$B$3035,0))} -> 269
A43: 249 | B43: 新浪科技 | C43: tech.sina.com.cn | D43: {=INDEX('原始数据'!C$2:C$3689,MATCH($C43,'原始数据'!$B$2:$B$3689,0))} -> 94933 | E43: {=INDEX('原始数据'!D$2:D$3689,MATCH($C43,'原始数据'!$B$2:$B$3689,0))} -> 151647 | F43: {=INDEX('原始数据'!E$2:E$3689,MATCH($C43,'原始数据'!$B$2:$B$3689,0))} -> 123290 | G43: {=INDEX('原始数据'!F$2:F$3689,MATCH($C43,'原始数据'!$B$2:$B$3689,0))} -> 98090 | H43: {=INDEX('原始数据'!G$2:G$3689,MATCH($C43,'原始数据'!$B$2:$B$3689,0))} -> 152658 | I43: {=INDEX('原始数据'!H$2:H$3689,MATCH($C43,'原始数据'!$B$2:$B$3689,0))} -> 125374 | J43: =IF(F43=0,I43*2,F43/$N$603+I43) -> 147521.79 | K43: =ROW(K43)-1 -> 42 | L43: {=INDEX(TOP3277!#REF!,MATCH(C43,TOP3277!$B$501:$B$3035,0))} -> 283
A44: 425 | B44: 熊猫办公 | C44: tukuppt.com | D44: {=INDEX('原始数据'!C$2:C$3689,MATCH($C44,'原始数据'!$B$2:$B$3689,0))} -> 254367 | E44: {=INDEX('原始数据'!D$2:D$3689,MATCH($C44,'原始数据'!$B$2:$B$3689,0))} -> 406327 | F44: {=INDEX('原始数据'!E$2:E$3689,MATCH($C44,'原始数据'!$B$2:$B$3689,0))} -> 330347 | G44: {=INDEX('原始数据'!F$2:F$3689,MATCH($C44,'原始数据'!$B$2:$B$3689,0))} -> 60539 | H44: {=INDEX('原始数据'!G$2:G$3689,MATCH($C44,'原始数据'!$B$2:$B$3689,0))} -> 87903 | I44: {=INDEX('原始数据'!H$2:H$3689,MATCH($C44,'原始数据'!$B$2:$B$3689,0))} -> 74221 | J44: =IF(F44=0,I44*2,F44/$N$603+I44) -> 133564.48 | K44: =ROW(K44)-1 -> 43 | L44: {=INDEX(TOP3277!#REF!,MATCH(C44,TOP3277!$B$501:$B$3035,0))} -> 296
A45: 574 | B45: 联想中国 | C45: lenovo.com.cn | D45: {=INDEX('原始数据'!C$2:C$3689,MATCH($C45,'原始数据'!$B$2:$B$3689,0))} -> 227209 | E45: {=INDEX('原始数据'!D$2:D$3689,MATCH($C45,'原始数据'!$B$2:$B$3689,0))} -> 362943 | F45: {=INDEX('原始数据'!E$2:E$3689,MATCH($C45,'原始数据'!$B$2:$B$3689,0))} -> 295076 | G45: {=INDEX('原始数据'!F$2:F$3689,MATCH($C45,'原始数据'!$B$2:$B$3689,0))} -> 66495 | H45: {=INDEX('原始数据'!G$2:G$3689,MATCH($C45,'原始数据'!$B$2:$B$3689,0))} -> 91818 | I45: {=INDEX('原始数据'!H$2:H$3689,MATCH($C45,'原始数据'!$B$2:$B$3689,0))} -> 79156.5 | J45: =IF(F45=0,I45*2,F45/$N$603+I45) -> 132163.9 | K45: =ROW(K45)-1 -> 44 | L45: {=INDEX(TOP3277!#REF!,MATCH(C45,TOP3277!$B$501:$B$3035,0))} -> 300
A46: 830 | B46: 测速网 | C46: speedtest.cn | D46: {=INDEX('原始数据'!C$2:C$3689,MATCH($C46,'原始数据'!$B$2:$B$3689,0))} -> 181856 | E46: {=INDEX('原始数据'!D$2:D$3689,MATCH($C46,'原始数据'!$B$2:$B$3689,0))} -> 290496 | F46: {=INDEX('原始数据'!E$2:E$3689,MATCH($C46,'原始数据'!$B$2:$B$3689,0))} -> 236176 | G46: {=INDEX('原始数据'!F$2:F$3689,MATCH($C46,'原始数据'!$B$2:$B$3689,0))} -> 72897 | H46: {=INDEX('原始数据'!G$2:G$3689,MATCH($C46,'原始数据'!$B$2:$B$3689,0))} -> 95743 | I46: {=INDEX('原始数据'!H$2:H$3689,MATCH($C46,'原始数据'!$B$2:$B$3689,0))} -> 84320 | J46: =IF(F46=0,I46*2,F46/$N$603+I46) -> 126746.61 | K46: =ROW(K46)-1 -> 45 | L46: {=INDEX(TOP3277!#REF!,MATCH(C46,TOP3277!$B$501:$B$3035,0))} -> 307
A47: 3367 | B47: UC浏览器网站 | C47: uc.cn | D47: {=INDEX('原始数据'!C$2:C$3689,MATCH($C47,'原始数据'!$B$2:$B$3689,0))} -> 501334 | E47: {=INDEX('原始数据'!D$2:D$3689,MATCH($C47,'原始数据'!$B$2:$B$3689,0))} -> 800834 | F47: {=INDEX('原始数据'!E$2:E$3689,MATCH($C47,'原始数据'!$B$2:$B$3689,0))} -> 651084 | G47: {=INDEX('原始数据'!F$2:F$3689,MATCH($C47,'原始数据'!$B$2:$B$3689,0))} -> 5386 | H47: {=INDEX('原始数据'!G$2:G$3689,MATCH($C47,'原始数据'!$B$2:$B$3689,0))} -> 7631 | I47: {=INDEX('原始数据'!H$2:H$3689,MATCH($C47,'原始数据'!$B$2:$B$3689,0))} -> 6508.5 | J47: =IF(F47=0,I47*2,F47/$N$603+I47) -> 123469.11 | K47: =ROW(K47)-1 -> 46 | L47: {=INDEX(TOP3277!#REF!,MATCH(C47,TOP3277!$B$501:$B$3035,0))} -> 295
A48: 271 | B48: Microsoft 支持 | C48: support.microsoft.com | D48: {=INDEX('原始数据'!C$2:C$3689,MATCH($C48,'原始数据'!$B$2:$B$3689,0))} -> 283337 | E48: {=INDEX('原始数据'!D$2:D$3689,MATCH($C48,'原始数据'!$B$2:$B$3689,0))} -> 452603 | F48: {=INDEX('原始数据'!E$2:E$3689,MATCH($C48,'原始数据'!$B$2:$B$3689,0))} -> 367970 | G48: {=INDEX('原始数据'!F$2:F$3689,MATCH($C48,'原始数据'!$B$2:$B$3689,0))} -> 45766 | H48: {=INDEX('原始数据'!G$2:G$3689,MATCH($C48,'原始数据'!$B$2:$B$3689,0))} -> 62431 | I48: {=INDEX('原始数据'!H$2:H$3689,MATCH($C48,'原始数据'!$B$2:$B$3689,0))} -> 54098.5 | J48: =IF(F48=0,I48*2,F48/$N$603+I48) -> 120200.56 | K48: =ROW(K48)-1 -> 47 | L48: {=INDEX(TOP3277!#REF!,MATCH(C48,TOP3277!$B$501:$B$3035,0))} -> #N/A
A49: 323 | B49: 51CTO技术博客 | C49: blog.51cto.com | D49: {=INDEX('原始数据'!C$2:C$3689,MATCH($C49,'原始数据'!$B$2:$B$3689,0))} -> 143319 | E49: {=INDEX('原始数据'!D$2:D$3689,MATCH($C49,'原始数据'!$B$2:$B$3689,0))} -> 228939 | F49: {=INDEX('原始数据'!E$2:E$3689,MATCH($C49,'原始数据'!$B$2:$B$3689,0))} -> 186129 | G49: {=INDEX('原始数据'!F$2:F$3689,MATCH($C49,'原始数据'!$B$2:$B$3689,0))} -> 66543 | H49: {=INDEX('原始数据'!G$2:G$3689,MATCH($C49,'原始数据'!$B$2:$B$3689,0))} -> 101055 | I49: {=INDEX('原始数据'!H$2:H$3689,MATCH($C49,'原始数据'!$B$2:$B$3689,0))} -> 83799 | J49: =IF(F49=0,I49*2,F49/$N$603+I49) -> 117235.18 | K49: =ROW(K49)-1 -> 48 | L49: {=INDEX(TOP3277!#REF!,MATCH(C49,TOP3277!$B$501:$B$3035,0))} -> 324
A50: 941 | B50: 精品源码论坛 | C50: adminn.cn | D50: {=INDEX('原始数据'!C$2:C$3689,MATCH($C50,'原始数据'!$B$2:$B$3689,0))} -> 301090 | E50: {=INDEX('原始数据'!D$2:D$3689,MATCH($C50,'原始数据'!$B$2:$B$3689,0))} -> 480964 | F50: {=INDEX('原始数据'!E$2:E$3689,MATCH($C50,'原始数据'!$B$2:$B$3689,0))} -> 391027 | G50: {=INDEX('原始数据'!F$2:F$3689,MATCH($C50,'原始数据'!$B$2:$B$3689,0))} -> 15724 | H50: {=INDEX('原始数据'!G$2:G$3689,MATCH($C50,'原始数据'!$B$2:$B$3689,0))} -> 58084 | I50: {=INDEX('原始数据'!H$2:H$3689,MATCH($C50,'原始数据'!$B$2:$B$3689,0))} -> 36904 | J50: =IF(F50=0,I50*2,F50/$N$603+I50) -> 107148.02 | K50: =ROW(K50)-1 -> 49 | L50: {=INDEX(TOP3277!#REF!,MATCH(C50,TOP3277!$B$501:$B$3035,0))} -> 329
A51: 794 | B51: 千库网 | C51: 588ku.com | D51: {=INDEX('原始数据'!C$2:C$3689,MATCH($C51,'原始数据'!$B$2:$B$3689,0))} -> 265077 | E51: {=INDEX('原始数据'!D$2:D$3689,MATCH($C51,'原始数据'!$B$2:$B$3689,0))} -> 423437 | F51: {=INDEX('原始数据'!E$2:E$3689,MATCH($C51,'原始数据'!$B$2:$B$3689,0))} -> 344257 | G51: {=INDEX('原始数据'!F$2:F$3689,MATCH($C51,'原始数据'!$B$2:$B$3689,0))} -> 35783 | H51: {=INDEX('原始数据'!G$2:G$3689,MATCH($C51,'原始数据'!$B$2:$B$3689,0))} -> 50820 | I51: {=INDEX('原始数据'!H$2:H$3689,MATCH($C51,'原始数据'!$B$2:$B$3689,0))} -> 43301.5 | J51: =IF(F51=0,I51*2,F51/$N$603+I51) -> 105143.77 | K51: =ROW(K51)-1 -> 50 | L51: {=INDEX(TOP3277!#REF!,MATCH(C51,TOP3277!$B$501:$B$3035,0))} -> 336
A52: 273 | B52: 希财网 | C52: csai.cn | D52: {=INDEX('原始数据'!C$2:C$3689,MATCH($C52,'原始数据'!$B$2:$B$3689,0))} -> 339993 | E52: {=INDEX('原始数据'!D$2:D$3689,MATCH($C52,'原始数据'!$B$2:$B$3689,0))} -> 543105 | F52: {=INDEX('原始数据'!E$2:E$3689,MATCH($C52,'原始数据'!$B$2:$B$3689,0))} -> 441549 | G52: {=INDEX('原始数据'!F$2:F$3689,MATCH($C52,'原始数据'!$B$2:$B$3689,0))} -> 17781 | H52: {=INDEX('原始数据'!G$2:G$3689,MATCH($C52,'原始数据'!$B$2:$B$3689,0))} -> 27204 | I52: {=INDEX('原始数据'!H$2:H$3689,MATCH($C52,'原始数据'!$B$2:$B$3689,0))} -> 22492.5 | J52: =IF(F52=0,I52*2,F52/$N$603+I52) -> 101812.28 | K52: =ROW(K52)-1 -> 51 | L52: {=INDEX(TOP3277!#REF!,MATCH(C52,TOP3277!$B$501:$B$3035,0))} -> 337
A53: 424 | B53: 爱给网 | C53: aigei.com | D53: {=INDEX('原始数据'!C$2:C$3689,MATCH($C53,'原始数据'!$B$2:$B$3689,0))} -> 132413 | E53: {=INDEX('原始数据'!D$2:D$3689,MATCH($C53,'原始数据'!$B$2:$B$3689,0))} -> 211515 | F53: {=INDEX('原始数据'!E$2:E$3689,MATCH($C53,'原始数据'!$B$2:$B$3689,0))} -> 171964 | G53: {=INDEX('原始数据'!F$2:F$3689,MATCH($C53,'原始数据'!$B$2:$B$3689,0))} -> 57645 | H53: {=INDEX('原始数据'!G$2:G$3689,MATCH($C53,'原始数据'!$B$2:$B$3689,0))} -> 81670 | I53: {=INDEX('原始数据'!H$2:H$3689,MATCH($C53,'原始数据'!$B$2:$B$3689,0))} -> 69657.5 | J53: =IF(F53=0,I53*2,F53/$N$603+I53) -> 100549.08 | K53: =ROW(K53)-1 -> 52 | L53: {=INDEX(TOP3277!#REF!,MATCH(C53,TOP3277!$B$501:$B$3035,0))} -> 363
... A55: 778 | B55: 网易邮箱网站 | C55: email.163.com | D55: {=INDEX('原始数据'!C$2:C$3689,MATCH($C55,'原始数据'!$B$2:$B$3689,0))} -> 191569 | E55: {=INDEX('原始数据'!D$2:D$3689,MATCH($C55,'原始数据'!$B$2:$B$3689,0))} -> 306013 | F55: {=INDEX('原始数据'!E$2:E$3689,MATCH($C55,'原始数据'!$B$2:$B$3689,0))} -> 248791 | G55: {=INDEX('原始数据'!F$2:F$3689,MATCH($C55,'原始数据'!$B$2:$B$3689,0))} -> 42953 | H55: {=INDEX('原始数据'!G$2:G$3689,MATCH($C55,'原始数据'!$B$2:$B$3689,0))} -> 61762 | I55: {=INDEX('原始数据'!H$2:H$3689,MATCH($C55,'原始数据'!$B$2:$B$3689,0))} -> 52357.5 | J55: =IF(F55=0,I55*2,F55/$N$603+I55) -> 97050.27 | K55: =ROW(K55)-1 -> 54 | L55: {=INDEX(TOP3277!#REF!,MATCH(C55,TOP3277!$B$501:$B$3035,0))} -> 365
A56: 2153 | B56: 菜鸟教程网 | C56: runoob.com | D56: 313699 | E56: 501103 | F56: =SUM(D56+E56)/2 -> 407401 | G56: 12995 | H56: 28575 | I56: =SUM(G56+H56)/2 -> 20785 | J56: =IF(F56=0,I56*2,F56/$N$603+I56) -> 93970.442 | K56: =ROW(K56)-1 -> 55 | L56: {=INDEX(TOP3277!#REF!,MATCH(C56,TOP3277!$B$501:$B$3035,0))} -> 466
A57: 774 | B57: 惠普中国 | C57: hp.com | D57: {=INDEX('原始数据'!C$2:C$3689,MATCH($C57,'原始数据'!$B$2:$B$3689,0))} -> 183529 | E57: {=INDEX('原始数据'!D$2:D$3689,MATCH($C57,'原始数据'!$B$2:$B$3689,0))} -> 293171 | F57: {=INDEX('原始数据'!E$2:E$3689,MATCH($C57,'原始数据'!$B$2:$B$3689,0))} -> 238350 | G57: {=INDEX('原始数据'!F$2:F$3689,MATCH($C57,'原始数据'!$B$2:$B$3689,0))} -> 34230 | H57: {=INDEX('原始数据'!G$2:G$3689,MATCH($C57,'原始数据'!$B$2:$B$3689,0))} -> 48218 | I57: {=INDEX('原始数据'!H$2:H$3689,MATCH($C57,'原始数据'!$B$2:$B$3689,0))} -> 41224 | J57: =IF(F57=0,I57*2,F57/$N$603+I57) -> 84041.151 | K57: =ROW(K57)-1 -> 56 | L57: {=INDEX(TOP3277!#REF!,MATCH(C57,TOP3277!$B$501:$B$3035,0))} -> 404
A58: 647 | B58: 我图网 | C58: ooopic.com | D58: {=INDEX('原始数据'!C$2:C$3689,MATCH($C58,'原始数据'!$B$2:$B$3689,0))} -> 139206 | E58: {=INDEX('原始数据'!D$2:D$3689,MATCH($C58,'原始数据'!$B$2:$B$3689,0))} -> 222370 | F58: {=INDEX('原始数据'!E$2:E$3689,MATCH($C58,'原始数据'!$B$2:$B$3689,0))} -> 180788 | G58: {=INDEX('原始数据'!F$2:F$3689,MATCH($C58,'原始数据'!$B$2:$B$3689,0))} -> 38888 | H58: {=INDEX('原始数据'!G$2:G$3689,MATCH($C58,'原始数据'!$B$2:$B$3689,0))} -> 59247 | I58: {=INDEX('原始数据'!H$2:H$3689,MATCH($C58,'原始数据'!$B$2:$B$3689,0))} -> 49067.5 | J58: =IF(F58=0,I58*2,F58/$N$603+I58) -> 81544.224 | K58: =ROW(K58)-1 -> 57 | L58: {=INDEX(TOP3277!#REF!,MATCH(C58,TOP3277!$B$501:$B$3035,0))} -> 413
A59: 623 | B59: TechWeb | C59: techweb.com.cn | D59: {=INDEX('原始数据'!C$2:C$3689,MATCH($C59,'原始数据'!$B$2:$B$3689,0))} -> 136627 | E59: {=INDEX('原始数据'!D$2:D$3689,MATCH($C59,'原始数据'!$B$2:$B$3689,0))} -> 218249 | F59: {=INDEX('原始数据'!E$2:E$3689,MATCH($C59,'原始数据'!$B$2:$B$3689,0))} -> 177438 | G59: {=INDEX('原始数据'!F$2:F$3689,MATCH($C59,'原始数据'!$B$2:$B$3689,0))} -> 39126 | H59: {=INDEX('原始数据'!G$2:G$3689,MATCH($C59,'原始数据'!$B$2:$B$3689,0))} -> 54570 | I59: {=INDEX('原始数据'!H$2:H$3689,MATCH($C59,'原始数据'!$B$2:$B$3689,0))} -> 46848 | J59: =IF(F59=0,I59*2,F59/$N$603+I59) -> 78722.93 | K59: =ROW(K59)-1 -> 58 | L59: {=INDEX(TOP3277!#REF!,MATCH(C59,TOP3277!$B$501:$B$3035,0))} -> 426
A60: 918 | B60: TP-LINK | C60: tp-link.com.cn | D60: {=INDEX('原始数据'!C$2:C$3689,MATCH($C60,'原始数据'!$B$2:$B$3689,0))} -> 167356 | E60: {=INDEX('原始数据'!D$2:D$3689,MATCH($C60,'原始数据'!$B$2:$B$3689,0))} -> 267333 | F60: {=INDEX('原始数据'!E$2:E$3689,MATCH($C60,'原始数据'!$B$2:$B$3689,0))} -> 217344.5 | G60: {=INDEX('原始数据'!F$2:F$3689,MATCH($C60,'原始数据'!$B$2:$B$3689,0))} -> 26756 | H60: {=INDEX('原始数据'!G$2:G$3689,MATCH($C60,'原始数据'!$B$2:$B$3689,0))} -> 39217 | I60: {=INDEX('原始数据'!H$2:H$3689,MATCH($C60,'原始数据'!$B$2:$B$3689,0))} -> 32986.5 | J60: =IF(F60=0,I60*2,F60/$N$603+I60) -> 72030.227 | K60: =ROW(K60)-1 -> 59 | L60: {=INDEX(TOP3277!#REF!,MATCH(C60,TOP3277!$B$501:$B$3035,0))} -> 441
A61: 820 | B61: 天极网 | C61: wap.yesky.com | D61: 43438 | E61: 69388 | F61: =SUM(D61+E61)/2 -> 56413 | G61: 51433 | H61: 70065 | I61: =SUM(G61+H61)/2 -> 60749 | J61: =IF(F61=0,I61*2,F61/$N$603+I61) -> 70883.021 | K61: =ROW(K61)-1 -> 60 | L61: {=INDEX(TOP3277!#REF!,MATCH(C61,TOP3277!$B$501:$B$3035,0))} -> #N/A
A62: 1216 | B62: 花瓣网 | C62: huaban.com | D62: {=INDEX('原始数据'!C$2:C$3689,MATCH($C62,'原始数据'!$B$2:$B$3689,0))} -> 184763 | E62: {=INDEX('原始数据'!D$2:D$3689,MATCH($C62,'原始数据'!$B$2:$B$3689,0))} -> 295141 | F62: {=INDEX('原始数据'!E$2:E$3689,MATCH($C62,'原始数据'!$B$2:$B$3689,0))} -> 239952 | G62: {=INDEX('原始数据'!F$2:F$3689,MATCH($C62,'原始数据'!$B$2:$B$3689,0))} -> 21135 | H62: {=INDEX('原始数据'!G$2:G$3689,MATCH($C62,'原始数据'!$B$2:$B$3689,0))} -> 30367 | I62: {=INDEX('原始数据'!H$2:H$3689,MATCH($C62,'原始数据'!$B$2:$B$3689,0))} -> 25751 | J62: =IF(F62=0,I62*2,F62/$N$603+I62) -> 68855.934 | K62: =ROW(K62)-1 -> 61 | L62: {=INDEX(TOP3277!#REF!,MATCH(C62,TOP3277!$B$501:$B$3035,0))} -> 455
A63: 952 | B63: 站长素材 | C63: sc.chinaz.com | D63: {=INDEX('原始数据'!C$2:C$3689,MATCH($C63,'原始数据'!$B$2:$B$3689,0))} -> 192160 | E63: {=INDEX('原始数据'!D$2:D$3689,MATCH($C63,'原始数据'!$B$2:$B$3689,0))} -> 306958 | F63: {=INDEX('原始数据'!E$2:E$3689,MATCH($C63,'原始数据'!$B$2:$B$3689,0))} -> 249559 | G63: {=INDEX('原始数据'!F$2:F$3689,MATCH($C63,'原始数据'!$B$2:$B$3689,0))} -> 18990 | H63: {=INDEX('原始数据'!G$2:G$3689,MATCH($C63,'原始数据'!$B$2:$B$3689,0))} -> 27441 | I63: {=INDEX('原始数据'!H$2:H$3689,MATCH($C63,'原始数据'!$B$2:$B$3689,0))} -> 23215.5 | J63: =IF(F63=0,I63*2,F63/$N$603+I63) -> 68046.234 | K63: =ROW(K63)-1 -> 62 | L63: {=INDEX(TOP3277!#REF!,MATCH(C63,TOP3277!$B$501:$B$3035,0))} -> 460
A64: 4468 | B64: MyPrice价格网 | C64: myprice.com.cn | D64: {=INDEX('原始数据'!C$2:C$3689,MATCH($C64,'原始数据'!$B$2:$B$3689,0))} -> 67457 | E64: {=INDEX('原始数据'!D$2:D$3689,MATCH($C64,'原始数据'!$B$2:$B$3689,0))} -> 107757 | F64: {=INDEX('原始数据'!E$2:E$3689,MATCH($C64,'原始数据'!$B$2:$B$3689,0))} -> 87607 | G64: {=INDEX('原始数据'!F$2:F$3689,MATCH($C64,'原始数据'!$B$2:$B$3689,0))} -> 40591 | H64: {=INDEX('原始数据'!G$2:G$3689,MATCH($C64,'原始数据'!$B$2:$B$3689,0))} -> 58416 | I64: {=INDEX('原始数据'!H$2:H$3689,MATCH($C64,'原始数据'!$B$2:$B$3689,0))} -> 49503.5 | J64: =IF(F64=0,I64*2,F64/$N$603+I64) -> 65241.206 | K64: =ROW(K64)-1 -> 63 | L64: {=INDEX(TOP3277!#REF!,MATCH(C64,TOP3277!$B$501:$B$3035,0))} -> 497
A65: 7491 | B65: 系统之家 | C65: xitongzhijia.net | D65: {=INDEX('原始数据'!C$2:C$3689,MATCH($C65,'原始数据'!$B$2:$B$3689,0))} -> 219396 | E65: {=INDEX('原始数据'!D$2:D$3689,MATCH($C65,'原始数据'!$B$2:$B$3689,0))} -> 350466 | F65: {=INDEX('原始数据'!E$2:E$3689,MATCH($C65,'原始数据'!$B$2:$B$3689,0))} -> 284931 | G65: {=INDEX('原始数据'!F$2:F$3689,MATCH($C65,'原始数据'!$B$2:$B$3689,0))} -> 8682 | H65: {=INDEX('原始数据'!G$2:G$3689,MATCH($C65,'原始数据'!$B$2:$B$3689,0))} -> 12550 | I65: {=INDEX('原始数据'!H$2:H$3689,MATCH($C65,'原始数据'!$B$2:$B$3689,0))} -> 10616 | J65: =IF(F65=0,I65*2,F65/$N$603+I65) -> 61800.953 | K65: =ROW(K65)-1 -> 64 | L65: {=INDEX(TOP3277!#REF!,MATCH(C65,TOP3277!$B$501:$B$3035,0))} -> 481
A66: 1110 | B66: 中国专业素材网 | C66: tooopen.com | D66: {=INDEX('原始数据'!C$2:C$3689,MATCH($C66,'原始数据'!$B$2:$B$3689,0))} -> 126116 | E66: {=INDEX('原始数据'!D$2:D$3689,MATCH($C66,'原始数据'!$B$2:$B$3689,0))} -> 201460 | F66: {=INDEX('原始数据'!E$2:E$3689,MATCH($C66,'原始数据'!$B$2:$B$3689,0))} -> 163788 | G66: {=INDEX('原始数据'!F$2:F$3689,MATCH($C66,'原始数据'!$B$2:$B$3689,0))} -> 21178 | H66: {=INDEX('原始数据'!G$2:G$3689,MATCH($C66,'原始数据'!$B$2:$B$3689,0))} -> 32871 | I66: {=INDEX('原始数据'!H$2:H$3689,MATCH($C66,'原始数据'!$B$2:$B$3689,0))} -> 27024.5 | J66: =IF(F66=0,I66*2,F66/$N$603+I66) -> 56447.347 | K66: =ROW(K66)-1 -> 65 | L66: {=INDEX(TOP3277!#REF!,MATCH(C66,TOP3277!$B$501:$B$3035,0))} -> 516
A67: 1859 | B67: 昵图网 | C67: nipic.com | D67: {=INDEX('原始数据'!C$2:C$3689,MATCH($C67,'原始数据'!$B$2:$B$3689,0))} -> 137670 | E67: {=INDEX('原始数据'!D$2:D$3689,MATCH($C67,'原始数据'!$B$2:$B$3689,0))} -> 219912 | F67: {=INDEX('原始数据'!E$2:E$3689,MATCH($C67,'原始数据'!$B$2:$B$3689,0))} -> 178791 | G67: {=INDEX('原始数据'!F$2:F$3689,MATCH($C67,'原始数据'!$B$2:$B$3689,0))} -> 20244 | H67: {=INDEX('原始数据'!G$2:G$3689,MATCH($C67,'原始数据'!$B$2:$B$3689,0))} -> 26385 | I67: {=INDEX('原始数据'!H$2:H$3689,MATCH($C67,'原始数据'!$B$2:$B$3689,0))} -> 23314.5 | J67: =IF(F67=0,I67*2,F67/$N$603+I67) -> 55432.483 | K67: =ROW(K67)-1 -> 66 | L67: {=INDEX(TOP3277!#REF!,MATCH(C67,TOP3277!$B$501:$B$3035,0))} -> 522
A68: 920 | B68: 盛火数据 | C68: 5v55.com | D68: {=INDEX('原始数据'!C$2:C$3689,MATCH($C68,'原始数据'!$B$2:$B$3689,0))} -> 111612 | E68: {=INDEX('原始数据'!D$2:D$3689,MATCH($C68,'原始数据'!$B$2:$B$3689,0))} -> 178290 | F68: {=INDEX('原始数据'!E$2:E$3689,MATCH($C68,'原始数据'!$B$2:$B$3689,0))} -> 144951 | G68: {=INDEX('原始数据'!F$2:F$3689,MATCH($C68,'原始数据'!$B$2:$B$3689,0))} -> 21665 | H68: {=INDEX('原始数据'!G$2:G$3689,MATCH($C68,'原始数据'!$B$2:$B$3689,0))} -> 36884 | I68: {=INDEX('原始数据'!H$2:H$3689,MATCH($C68,'原始数据'!$B$2:$B$3689,0))} -> 29274.5 | J68: =IF(F68=0,I68*2,F68/$N$603+I68) -> 55313.471 | K68: =ROW(K68)-1 -> 67 | L68: {=INDEX(TOP3277!#REF!,MATCH(C68,TOP3277!$B$501:$B$3035,0))} -> 526
A69: 1404 | B69: NVIDIA公司 | C69: nvidia.cn | D69: 90605 | E69: 144733 | F69: =SUM(D69+E69)/2 -> 117669 | G69: 31163 | H69: 36992 | I69: =SUM(G69+H69)/2 -> 34077.5 | J69: =IF(F69=0,I69*2,F69/$N$603+I69) -> 55215.538 | K69: =ROW(K69)-1 -> 68 | L69: {=INDEX(TOP3277!#REF!,MATCH(C69,TOP3277!$B$501:$B$3035,0))} -> 594
A70: 1081 | B70: IT之家 | C70: ithome.com | D70: {=INDEX('原始数据'!C$2:C$3689,MATCH($C70,'原始数据'!$B$2:$B$3689,0))} -> 121443 | E70: {=INDEX('原始数据'!D$2:D$3689,MATCH($C70,'原始数据'!$B$2:$B$3689,0))} -> 193997 | F70: {=INDEX('原始数据'!E$2:E$3689,MATCH($C70,'原始数据'!$B$2:$B$3689,0))} -> 157720 | G70: {=INDEX('原始数据'!F$2:F$3689,MATCH($C70,'原始数据'!$B$2:$B$3689,0))} -> 21500 | H70: {=INDEX('原始数据'!G$2:G$3689,MATCH($C70,'原始数据'!$B$2:$B$3689,0))} -> 29468 | I70: {=INDEX('原始数据'!H$2:H$3689,MATCH($C70,'原始数据'!$B$2:$B$3689,0))} -> 25484 | J70: =IF(F70=0,I70*2,F70/$N$603+I70) -> 53816.792 | K70: =ROW(K70)-1 -> 69 | L70: {=INDEX(TOP3277!#REF!,MATCH(C70,TOP3277!$B$501:$B$3035,0))} -> 531
A71: 1013 | B71: 红动网 | C71: redocn.com | D71: {=INDEX('原始数据'!C$2:C$3689,MATCH($C71,'原始数据'!$B$2:$B$3689,0))} -> 93881 | E71: {=INDEX('原始数据'!D$2:D$3689,MATCH($C71,'原始数据'!$B$2:$B$3689,0))} -> 149965 | F71: {=INDEX('原始数据'!E$2:E$3689,MATCH($C71,'原始数据'!$B$2:$B$3689,0))} -> 121923 | G71: {=INDEX('原始数据'!F$2:F$3689,MATCH($C71,'原始数据'!$B$2:$B$3689,0))} -> 24744 | H71: {=INDEX('原始数据'!G$2:G$3689,MATCH($C71,'原始数据'!$B$2:$B$3689,0))} -> 38713 | I71: {=INDEX('原始数据'!H$2:H$3689,MATCH($C71,'原始数据'!$B$2:$B$3689,0))} -> 31728.5 | J71: =IF(F71=0,I71*2,F71/$N$603+I71) -> 53630.726 | K71: =ROW(K71)-1 -> 70 | L71: {=INDEX(TOP3277!#REF!,MATCH(C71,TOP3277!$B$501:$B$3035,0))} -> 551
A72: 1173 | B72: 觅元素 | C72: 51yuansu.com | D72: 80882 | E72: 129202 | F72: =SUM(D72+E72)/2 -> 105042 | G72: 28718 | H72: 40153 | I72: =SUM(G72+H72)/2 -> 34435.5 | J72: =IF(F72=0,I72*2,F72/$N$603+I72) -> 53305.226 | K72: =ROW(K72)-1 -> 71 | L72: {=INDEX(TOP3277!#REF!,MATCH(C72,TOP3277!$B$501:$B$3035,0))} -> 600
A73: 1794 | B73: 站长素材网 | C73: m.sc.chinaz.com | D73: 123775 | E73: 197719 | F73: =SUM(D73+E73)/2 -> 160747 | G73: 18583 | H73: 27604 | I73: =SUM(G73+H73)/2 -> 23093.5 | J73: =IF(F73=0,I73*2,F73/$N$603+I73) -> 51970.062 | K73: =ROW(K73)-1 -> 72 | L73: {=INDEX(TOP3277!#REF!,MATCH(C73,TOP3277!$B$501:$B$3035,0))} -> #N/A
A74: 1493 | B74: 网易 | C74: netease.com | D74: 145594 | E74: 232572 | F74: =SUM(D74+E74)/2 -> 189083 | G74: 9257 | H74: 13692 | I74: =SUM(G74+H74)/2 -> 11474.5 | J74: =IF(F74=0,I74*2,F74/$N$603+I74) -> 45441.336 | K74: =ROW(K74)-1 -> 73 | L74: {=INDEX(TOP3277!#REF!,MATCH(C74,TOP3277!$B$501:$B$3035,0))} -> #N/A
A75: 1815 | B75: 华硕 | C75: asus.com.cn | D75: 87803 | E75: 140257 | F75: =SUM(D75+E75)/2 -> 114030 | G75: 21351 | H75: 27395 | I75: =SUM(G75+H75)/2 -> 24373 | J75: =IF(F75=0,I75*2,F75/$N$603+I75) -> 44857.329 | K75: =ROW(K75)-1 -> 74 | L75: {=INDEX(TOP3277!#REF!,MATCH(C75,TOP3277!$B$501:$B$3035,0))} -> 866
A76: 1446 | B76: SO JSON在线 | C76: sojson.com | D76: {=INDEX('原始数据'!C$2:C$3689,MATCH($C76,'原始数据'!$B$2:$B$3689,0))} -> 118494 | E76: {=INDEX('原始数据'!D$2:D$3689,MATCH($C76,'原始数据'!$B$2:$B$3689,0))} -> 189280 | F76: {=INDEX('原始数据'!E$2:E$3689,MATCH($C76,'原始数据'!$B$2:$B$3689,0))} -> 153887 | G76: {=INDEX('原始数据'!F$2:F$3689,MATCH($C76,'原始数据'!$B$2:$B$3689,0))} -> 11699 | H76: {=INDEX('原始数据'!G$2:G$3689,MATCH($C76,'原始数据'!$B$2:$B$3689,0))} -> 18514 | I76: {=INDEX('原始数据'!H$2:H$3689,MATCH($C76,'原始数据'!$B$2:$B$3689,0))} -> 15106.5 | J76: =IF(F76=0,I76*2,F76/$N$603+I76) -> 42750.733 | K76: =ROW(K76)-1 -> 75 | L76: {=INDEX(TOP3277!#REF!,MATCH(C76,TOP3277!$B$501:$B$3035,0))} -> 616
A77: 817 | B77: 源码之家网站 | C77: mycodes.net | D77: {=INDEX('原始数据'!C$2:C$3689,MATCH($C77,'原始数据'!$B$2:$B$3689,0))} -> 65763 | E77: {=INDEX('原始数据'!D$2:D$3689,MATCH($C77,'原始数据'!$B$2:$B$3689,0))} -> 105049 | F77: {=INDEX('原始数据'!E$2:E$3689,MATCH($C77,'原始数据'!$B$2:$B$3689,0))} -> 85406 | G77: {=INDEX('原始数据'!F$2:F$3689,MATCH($C77,'原始数据'!$B$2:$B$3689,0))} -> 21704 | H77: {=INDEX('原始数据'!G$2:G$3689,MATCH($C77,'原始数据'!$B$2:$B$3689,0))} -> 32787 | I77: {=INDEX('原始数据'!H$2:H$3689,MATCH($C77,'原始数据'!$B$2:$B$3689,0))} -> 27245.5 | J77: =IF(F77=0,I77*2,F77/$N$603+I77) -> 42587.818 | K77: =ROW(K77)-1 -> 76 | L77: {=INDEX(TOP3277!#REF!,MATCH(C77,TOP3277!$B$501:$B$3035,0))} -> 646
A78: 1331 | B78: 第一PPT | C78: 1ppt.com | D78: {=INDEX('原始数据'!C$2:C$3689,MATCH($C78,'原始数据'!$B$2:$B$3689,0))} -> 85627 | E78: {=INDEX('原始数据'!D$2:D$3689,MATCH($C78,'原始数据'!$B$2:$B$3689,0))} -> 136781 | F78: {=INDEX('原始数据'!E$2:E$3689,MATCH($C78,'原始数据'!$B$2:$B$3689,0))} -> 111204 | G78: {=INDEX('原始数据'!F$2:F$3689,MATCH($C78,'原始数据'!$B$2:$B$3689,0))} -> 19062 | H78: {=INDEX('原始数据'!G$2:G$3689,MATCH($C78,'原始数据'!$B$2:$B$3689,0))} -> 23315 | I78: {=INDEX('原始数据'!H$2:H$3689,MATCH($C78,'原始数据'!$B$2:$B$3689,0))} -> 21188.5 | J78: =IF(F78=0,I78*2,F78/$N$603+I78) -> 41165.166 | K78: =ROW(K78)-1 -> 77 | L78: {=INDEX(TOP3277!#REF!,MATCH(C78,TOP3277!$B$501:$B$3035,0))} -> 650
A79: 1042 | B79: 云服务器 | C79: ctyun.cn | D79: {=INDEX('原始数据'!C$2:C$3689,MATCH($C79,'原始数据'!$B$2:$B$3689,0))} -> 53611 | E79: {=INDEX('原始数据'!D$2:D$3689,MATCH($C79,'原始数据'!$B$2:$B$3689,0))} -> 85641 | F79: {=INDEX('原始数据'!E$2:E$3689,MATCH($C79,'原始数据'!$B$2:$B$3689,0))} -> 69626 | G79: {=INDEX('原始数据'!F$2:F$3689,MATCH($C79,'原始数据'!$B$2:$B$3689,0))} -> 25159 | H79: {=INDEX('原始数据'!G$2:G$3689,MATCH($C79,'原始数据'!$B$2:$B$3689,0))} -> 31434 | I79: {=INDEX('原始数据'!H$2:H$3689,MATCH($C79,'原始数据'!$B$2:$B$3689,0))} -> 28296.5 | J79: =IF(F79=0,I79*2,F79/$N$603+I79) -> 40804.102 | K79: =ROW(K79)-1 -> 78 | L79: {=INDEX(TOP3277!#REF!,MATCH(C79,TOP3277!$B$501:$B$3035,0))} -> 676
A80: 2090 | B80: 包图网 | C80: ibaotu.com | D80: {=INDEX('原始数据'!C$2:C$3689,MATCH($C80,'原始数据'!$B$2:$B$3689,0))} -> 128868 | E80: {=INDEX('原始数据'!D$2:D$3689,MATCH($C80,'原始数据'!$B$2:$B$3689,0))} -> 205854 | F80: {=INDEX('原始数据'!E$2:E$3689,MATCH($C80,'原始数据'!$B$2:$B$3689,0))} -> 167361 | G80: {=INDEX('原始数据'!F$2:F$3689,MATCH($C80,'原始数据'!$B$2:$B$3689,0))} -> 8585 | H80: {=INDEX('原始数据'!G$2:G$3689,MATCH($C80,'原始数据'!$B$2:$B$3689,0))} -> 12443 | I80: {=INDEX('原始数据'!H$2:H$3689,MATCH($C80,'原始数据'!$B$2:$B$3689,0))} -> 10514 | J80: =IF(F80=0,I80*2,F80/$N$603+I80) -> 40578.7 | K80: =ROW(K80)-1 -> 79 | L80: {=INDEX(TOP3277!#REF!,MATCH(C80,TOP3277!$B$501:$B$3035,0))} -> 637
A81: 1288 | B81: 六图网 | C81: 16pic.com | D81: {=INDEX('原始数据'!C$2:C$3689,MATCH($C81,'原始数据'!$B$2:$B$3689,0))} -> 60951 | E81: {=INDEX('原始数据'!D$2:D$3689,MATCH($C81,'原始数据'!$B$2:$B$3689,0))} -> 97365 | F81: {=INDEX('原始数据'!E$2:E$3689,MATCH($C81,'原始数据'!$B$2:$B$3689,0))} -> 79158 | G81: {=INDEX('原始数据'!F$2:F$3689,MATCH($C81,'原始数据'!$B$2:$B$3689,0))} -> 20416 | H81: {=INDEX('原始数据'!G$2:G$3689,MATCH($C81,'原始数据'!$B$2:$B$3689,0))} -> 31312 | I81: {=INDEX('原始数据'!H$2:H$3689,MATCH($C81,'原始数据'!$B$2:$B$3689,0))} -> 25864 | J81: =IF(F81=0,I81*2,F81/$N$603+I81) -> 40083.929 | K81: =ROW(K81)-1 -> 80 | L81: {=INDEX(TOP3277!#REF!,MATCH(C81,TOP3277!$B$501:$B$3035,0))} -> 678
A82: 1200 | B82: 图行天下图库 | C82: photophoto.cn | D82: {=INDEX('原始数据'!C$2:C$3689,MATCH($C82,'原始数据'!$B$2:$B$3689,0))} -> 85942 | E82: {=INDEX('原始数据'!D$2:D$3689,MATCH($C82,'原始数据'!$B$2:$B$3689,0))} -> 137284 | F82: {=INDEX('原始数据'!E$2:E$3689,MATCH($C82,'原始数据'!$B$2:$B$3689,0))} -> 111613 | G82: {=INDEX('原始数据'!F$2:F$3689,MATCH($C82,'原始数据'!$B$2:$B$3689,0))} -> 17024 | H82: {=INDEX('原始数据'!G$2:G$3689,MATCH($C82,'原始数据'!$B$2:$B$3689,0))} -> 22607 | I82: {=INDEX('原始数据'!H$2:H$3689,MATCH($C82,'原始数据'!$B$2:$B$3689,0))} -> 19815.5 | J82: =IF(F82=0,I82*2,F82/$N$603+I82) -> 39865.639 | K82: =ROW(K82)-1 -> 81 | L82: {=INDEX(TOP3277!#REF!,MATCH(C82,TOP3277!$B$501:$B$3035,0))} -> 668
A83: 1063 | B83: 超能网 | C83: expreview.com | D83: {=INDEX('原始数据'!C$2:C$3689,MATCH($C83,'原始数据'!$B$2:$B$3689,0))} -> 46153 | E83: {=INDEX('原始数据'!D$2:D$3689,MATCH($C83,'原始数据'!$B$2:$B$3689,0))} -> 73729 | F83: {=INDEX('原始数据'!E$2:E$3689,MATCH($C83,'原始数据'!$B$2:$B$3689,0))} -> 59941 | G83: {=INDEX('原始数据'!F$2:F$3689,MATCH($C83,'原始数据'!$B$2:$B$3689,0))} -> 22965 | H83: {=INDEX('原始数据'!G$2:G$3689,MATCH($C83,'原始数据'!$B$2:$B$3689,0))} -> 33056 | I83: {=INDEX('原始数据'!H$2:H$3689,MATCH($C83,'原始数据'!$B$2:$B$3689,0))} -> 28010.5 | J83: =IF(F83=0,I83*2,F83/$N$603+I83) -> 38778.29 | K83: =ROW(K83)-1 -> 82 | L83: {=INDEX(TOP3277!#REF!,MATCH(C83,TOP3277!$B$501:$B$3035,0))} -> #N/A
A84: 1144 | B84: 我图网素材搜索 | C84: so.ooopic.com | D84: {=INDEX('原始数据'!C$2:C$3689,MATCH($C84,'原始数据'!$B$2:$B$3689,0))} -> 92129 | E84: {=INDEX('原始数据'!D$2:D$3689,MATCH($C84,'原始数据'!$B$2:$B$3689,0))} -> 147167 | F84: {=INDEX('原始数据'!E$2:E$3689,MATCH($C84,'原始数据'!$B$2:$B$3689,0))} -> 119648 | G84: {=INDEX('原始数据'!F$2:F$3689,MATCH($C84,'原始数据'!$B$2:$B$3689,0))} -> 14594 | H84: {=INDEX('原始数据'!G$2:G$3689,MATCH($C84,'原始数据'!$B$2:$B$3689,0))} -> 18022 | I84: {=INDEX('原始数据'!H$2:H$3689,MATCH($C84,'原始数据'!$B$2:$B$3689,0))} -> 16308 | J84: =IF(F84=0,I84*2,F84/$N$603+I84) -> 37801.545 | K84: =ROW(K84)-1 -> 83 | L84: {=INDEX(TOP3277!#REF!,MATCH(C84,TOP3277!$B$501:$B$3035,0))} -> 688
A85: 1392 | B85: ProcessOn绘图平台 | C85: processon.com | D85: {=INDEX('原始数据'!C$2:C$3689,MATCH($C85,'原始数据'!$B$2:$B$3689,0))} -> 42023 | E85: {=INDEX('原始数据'!D$2:D$3689,MATCH($C85,'原始数据'!$B$2:$B$3689,0))} -> 67129 | F85: {=INDEX('原始数据'!E$2:E$3689,MATCH($C85,'原始数据'!$B$2:$B$3689,0))} -> 54576 | G85: {=INDEX('原始数据'!F$2:F$3689,MATCH($C85,'原始数据'!$B$2:$B$3689,0))} -> 21184 | H85: {=INDEX('原始数据'!G$2:G$3689,MATCH($C85,'原始数据'!$B$2:$B$3689,0))} -> 33897 | I85: {=INDEX('原始数据'!H$2:H$3689,MATCH($C85,'原始数据'!$B$2:$B$3689,0))} -> 27540.5 | J85: =IF(F85=0,I85*2,F85/$N$603+I85) -> 37344.523 | K85: =ROW(K85)-1 -> 84 | L85: {=INDEX(TOP3277!#REF!,MATCH(C85,TOP3277!$B$501:$B$3035,0))} -> 717
A86: 3936 | B86: 稿定设计网 | C86: gaoding.com | D86: 69495 | E86: 111015 | F86: =SUM(D86+E86)/2 -> 90255 | G86: 16813 | H86: 25130 | I86: =SUM(G86+H86)/2 -> 20971.5 | J86: =IF(F86=0,I86*2,F86/$N$603+I86) -> 37184.892 | K86: =ROW(K86)-1 -> 85 | L86: {=INDEX(TOP3277!#REF!,MATCH(C86,TOP3277!$B$501:$B$3035,0))} -> #N/A
A87: 1454 | B87: 凤凰科技 | C87: tech.ifeng.com | D87: {=INDEX('原始数据'!C$2:C$3689,MATCH($C87,'原始数据'!$B$2:$B$3689,0))} -> 76904 | E87: {=INDEX('原始数据'!D$2:D$3689,MATCH($C87,'原始数据'!$B$2:$B$3689,0))} -> 122846 | F87: {=INDEX('原始数据'!E$2:E$3689,MATCH($C87,'原始数据'!$B$2:$B$3689,0))} -> 99875 | G87: {=INDEX('原始数据'!F$2:F$3689,MATCH($C87,'原始数据'!$B$2:$B$3689,0))} -> 14692 | H87: {=INDEX('原始数据'!G$2:G$3689,MATCH($C87,'原始数据'!$B$2:$B$3689,0))} -> 22674 | I87: {=INDEX('原始数据'!H$2:H$3689,MATCH($C87,'原始数据'!$B$2:$B$3689,0))} -> 18683 | J87: =IF(F87=0,I87*2,F87/$N$603+I87) -> 36624.527 | K87: =ROW(K87)-1 -> 86 | L87: {=INDEX(TOP3277!#REF!,MATCH(C87,TOP3277!$B$501:$B$3035,0))} -> 713
A88: 1386 | B88: 创客贴 | C88: chuangkit.com | D88: {=INDEX('原始数据'!C$2:C$3689,MATCH($C88,'原始数据'!$B$2:$B$3689,0))} -> 47693 | E88: {=INDEX('原始数据'!D$2:D$3689,MATCH($C88,'原始数据'!$B$2:$B$3689,0))} -> 76185 | F88: {=INDEX('原始数据'!E$2:E$3689,MATCH($C88,'原始数据'!$B$2:$B$3689,0))} -> 61939 | G88: {=INDEX('原始数据'!F$2:F$3689,MATCH($C88,'原始数据'!$B$2:$B$3689,0))} -> 17965 | H88: {=INDEX('原始数据'!G$2:G$3689,MATCH($C88,'原始数据'!$B$2:$B$3689,0))} -> 30790 | I88: {=INDEX('原始数据'!H$2:H$3689,MATCH($C88,'原始数据'!$B$2:$B$3689,0))} -> 24377.5 | J88: =IF(F88=0,I88*2,F88/$N$603+I88) -> 35504.211 | K88: =ROW(K88)-1 -> 87 | L88: {=INDEX(TOP3277!#REF!,MATCH(C88,TOP3277!$B$501:$B$3035,0))} -> 732
A89: 323 | B89: 火狐浏览器官网 | C89: firefox.com.cn | D89: {=INDEX('原始数据'!C$2:C$3689,MATCH($C89,'原始数据'!$B$2:$B$3689,0))} -> 60782 | E89: {=INDEX('原始数据'!D$2:D$3689,MATCH($C89,'原始数据'!$B$2:$B$3689,0))} -> 97096 | F89: {=INDEX('原始数据'!E$2:E$3689,MATCH($C89,'原始数据'!$B$2:$B$3689,0))} -> 78939 | G89: {=INDEX('原始数据'!F$2:F$3689,MATCH($C89,'原始数据'!$B$2:$B$3689,0))} -> 16658 | H89: {=INDEX('原始数据'!G$2:G$3689,MATCH($C89,'原始数据'!$B$2:$B$3689,0))} -> 22065 | I89: {=INDEX('原始数据'!H$2:H$3689,MATCH($C89,'原始数据'!$B$2:$B$3689,0))} -> 19361.5 | J89: =IF(F89=0,I89*2,F89/$N$603+I89) -> 33542.088 | K89: =ROW(K89)-1 -> 88 | L89: {=INDEX(TOP3277!#REF!,MATCH(C89,TOP3277!$B$501:$B$3035,0))} -> 753
A90: 996 | B90: WordPress | C90: wordpress.com | D90: 63334 | E90: 101168 | F90: =SUM(D90+E90)/2 -> 82251 | G90: 14995 | H90: 22420 | I90: =SUM(G90+H90)/2 -> 18707.5 | J90: =IF(F90=0,I90*2,F90/$N$603+I90) -> 33483.055 | K90: =ROW(K90)-1 -> 89 | L90: {=INDEX(TOP3277!#REF!,MATCH(C90,TOP3277!$B$501:$B$3035,0))} -> #N/A
A91: 2067 | B91: wifi万能钥匙 | C91: wifi.com | D91: {=INDEX('原始数据'!C$2:C$3689,MATCH($C91,'原始数据'!$B$2:$B$3689,0))} -> 19877 | E91: {=INDEX('原始数据'!D$2:D$3689,MATCH($C91,'原始数据'!$B$2:$B$3689,0))} -> 31751 | F91: {=INDEX('原始数据'!E$2:E$3689,MATCH($C91,'原始数据'!$B$2:$B$3689,0))} -> 25814 | G91: {=INDEX('原始数据'!F$2:F$3689,MATCH($C91,'原始数据'!$B$2:$B$3689,0))} -> 25754 | H91: {=INDEX('原始数据'!G$2:G$3689,MATCH($C91,'原始数据'!$B$2:$B$3689,0))} -> 31512 | I91: {=INDEX('原始数据'!H$2:H$3689,MATCH($C91,'原始数据'!$B$2:$B$3689,0))} -> 28633 | J91: =IF(F91=0,I91*2,F91/$N$603+I91) -> 33270.222 | K91: =ROW(K91)-1 -> 90 | L91: {=INDEX(TOP3277!#REF!,MATCH(C91,TOP3277!$B$501:$B$3035,0))} -> 783
A92: 1151 | B92: 3D溜溜网 | C92: 3d66.com | D92: {=INDEX('原始数据'!C$2:C$3689,MATCH($C92,'原始数据'!$B$2:$B$3689,0))} -> 55526 | E92: {=INDEX('原始数据'!D$2:D$3689,MATCH($C92,'原始数据'!$B$2:$B$3689,0))} -> 88694 | F92: {=INDEX('原始数据'!E$2:E$3689,MATCH($C92,'原始数据'!$B$2:$B$3689,0))} -> 72110 | G92: {=INDEX('原始数据'!F$2:F$3689,MATCH($C92,'原始数据'!$B$2:$B$3689,0))} -> 16443 | H92: {=INDEX('原始数据'!G$2:G$3689,MATCH($C92,'原始数据'!$B$2:$B$3689,0))} -> 23635 | I92: {=INDEX('原始数据'!H$2:H$3689,MATCH($C92,'原始数据'!$B$2:$B$3689,0))} -> 20039 | J92: =IF(F92=0,I92*2,F92/$N$603+I92) -> 32992.827 | K92: =ROW(K92)-1 -> 91 | L92: {=INDEX(TOP3277!#REF!,MATCH(C92,TOP3277!$B$501:$B$3035,0))} -> 768
A93: 1618 | B93: 腾讯电脑管家 | C93: guanjia.qq.com | D93: {=INDEX('原始数据'!C$2:C$3689,MATCH($C93,'原始数据'!$B$2:$B$3689,0))} -> 70933 | E93: {=INDEX('原始数据'!D$2:D$3689,MATCH($C93,'原始数据'!$B$2:$B$3689,0))} -> 113307 | F93: {=INDEX('原始数据'!E$2:E$3689,MATCH($C93,'原始数据'!$B$2:$B$3689,0))} -> 92120 | G93: {=INDEX('原始数据'!F$2:F$3689,MATCH($C93,'原始数据'!$B$2:$B$3689,0))} -> 14393 | H93: {=INDEX('原始数据'!G$2:G$3689,MATCH($C93,'原始数据'!$B$2:$B$3689,0))} -> 17760 | I93: {=INDEX('原始数据'!H$2:H$3689,MATCH($C93,'原始数据'!$B$2:$B$3689,0))} -> 16076.5 | J93: =IF(F93=0,I93*2,F93/$N$603+I93) -> 32624.92 | K93: =ROW(K93)-1 -> 92 | L93: {=INDEX(TOP3277!#REF!,MATCH(C93,TOP3277!$B$501:$B$3035,0))} -> 759
A94: 272 | B94: 百度开放平台 | C94: opendata.baidu.com | F94: =SUM(D94+E94)/2 -> 0 | G94: 13983 | H94: 17768 | I94: =SUM(G94+H94)/2 -> 15875.5 | J94: =IF(F94=0,I94*2,F94/$N$603+I94) -> 31751 | K94: =ROW(K94)-1 -> 93 | L94: {=INDEX(TOP3277!#REF!,MATCH(C94,TOP3277!$B$501:$B$3035,0))} -> #N/A
A95: 1480 | B95: 设计本 | C95: shejiben.com | D95: {=INDEX('原始数据'!C$2:C$3689,MATCH($C95,'原始数据'!$B$2:$B$3689,0))} -> 39928 | E95: {=INDEX('原始数据'!D$2:D$3689,MATCH($C95,'原始数据'!$B$2:$B$3689,0))} -> 63782 | F95: {=INDEX('原始数据'!E$2:E$3689,MATCH($C95,'原始数据'!$B$2:$B$3689,0))} -> 51855 | G95: {=INDEX('原始数据'!F$2:F$3689,MATCH($C95,'原始数据'!$B$2:$B$3689,0))} -> 17832 | H95: {=INDEX('原始数据'!G$2:G$3689,MATCH($C95,'原始数据'!$B$2:$B$3689,0))} -> 25100 | I95: {=INDEX('原始数据'!H$2:H$3689,MATCH($C95,'原始数据'!$B$2:$B$3689,0))} -> 21466 | J95: =IF(F95=0,I95*2,F95/$N$603+I95) -> 30781.223 | K95: =ROW(K95)-1 -> 94 | L95: {=INDEX(TOP3277!#REF!,MATCH(C95,TOP3277!$B$501:$B$3035,0))} -> 799
A96: 1280 | B96: 伙伴办公 | C96: huoban.com | D96: {=INDEX('原始数据'!C$2:C$3689,MATCH($C96,'原始数据'!$B$2:$B$3689,0))} -> 37949 | E96: {=INDEX('原始数据'!D$2:D$3689,MATCH($C96,'原始数据'!$B$2:$B$3689,0))} -> 60619 | F96: {=INDEX('原始数据'!E$2:E$3689,MATCH($C96,'原始数据'!$B$2:$B$3689,0))} -> 49284 | G96: {=INDEX('原始数据'!F$2:F$3689,MATCH($C96,'原始数据'!$B$2:$B$3689,0))} -> 17328 | H96: {=INDEX('原始数据'!G$2:G$3689,MATCH($C96,'原始数据'!$B$2:$B$3689,0))} -> 25059 | I96: {=INDEX('原始数据'!H$2:H$3689,MATCH($C96,'原始数据'!$B$2:$B$3689,0))} -> 21193.5 | J96: =IF(F96=0,I96*2,F96/$N$603+I96) -> 30046.869 | K96: =ROW(K96)-1 -> 95 | L96: {=INDEX(TOP3277!#REF!,MATCH(C96,TOP3277!$B$501:$B$3035,0))} -> 813
A97: 1437 | B97: 草料网 | C97: cli.im | D97: {=INDEX('原始数据'!C$2:C$3689,MATCH($C97,'原始数据'!$B$2:$B$3689,0))} -> 55614 | E97: {=INDEX('原始数据'!D$2:D$3689,MATCH($C97,'原始数据'!$B$2:$B$3689,0))} -> 88839 | F97: {=INDEX('原始数据'!E$2:E$3689,MATCH($C97,'原始数据'!$B$2:$B$3689,0))} -> 72226.5 | G97: {=INDEX('原始数据'!F$2:F$3689,MATCH($C97,'原始数据'!$B$2:$B$3689,0))} -> 15236 | H97: {=INDEX('原始数据'!G$2:G$3689,MATCH($C97,'原始数据'!$B$2:$B$3689,0))} -> 18537 | I97: {=INDEX('原始数据'!H$2:H$3689,MATCH($C97,'原始数据'!$B$2:$B$3689,0))} -> 16886.5 | J97: =IF(F97=0,I97*2,F97/$N$603+I97) -> 29861.255 | K97: =ROW(K97)-1 -> 96 | L97: {=INDEX(TOP3277!#REF!,MATCH(C97,TOP3277!$B$501:$B$3035,0))} -> 806
A98: 809 | B98: Java编程 | C98: iteye.com | D98: {=INDEX('原始数据'!C$2:C$3689,MATCH($C98,'原始数据'!$B$2:$B$3689,0))} -> 3221 | E98: {=INDEX('原始数据'!D$2:D$3689,MATCH($C98,'原始数据'!$B$2:$B$3689,0))} -> 5143 | F98: {=INDEX('原始数据'!E$2:E$3689,MATCH($C98,'原始数据'!$B$2:$B$3689,0))} -> 4182 | G98: {=INDEX('原始数据'!F$2:F$3689,MATCH($C98,'原始数据'!$B$2:$B$3689,0))} -> 22876 | H98: {=INDEX('原始数据'!G$2:G$3689,MATCH($C98,'原始数据'!$B$2:$B$3689,0))} -> 35140 | I98: {=INDEX('原始数据'!H$2:H$3689,MATCH($C98,'原始数据'!$B$2:$B$3689,0))} -> 29008 | J98: =IF(F98=0,I98*2,F98/$N$603+I98) -> 29759.254 | K98: =ROW(K98)-1 -> 97 | L98: {=INDEX(TOP3277!#REF!,MATCH(C98,TOP3277!$B$501:$B$3035,0))} -> 839
A99: 1032 | B99: 英特尔 | C99: intel.com | D99: 30328 | E99: 48448 | F99: =SUM(D99+E99)/2 -> 39388 | G99: 18735 | H99: 25146 | I99: =SUM(G99+H99)/2 -> 21940.5 | J99: =IF(F99=0,I99*2,F99/$N$603+I99) -> 29016.153 | K99: =ROW(K99)-1 -> 98 | L99: {=INDEX(TOP3277!#REF!,MATCH(C99,TOP3277!$B$501:$B$3035,0))} -> 966
A100: 1221 | B100: 电脑之家 | C100: pchome.net | D100: {=INDEX('原始数据'!C$2:C$3689,MATCH($C100,'原始数据'!$B$2:$B$3689,0))} -> 72858 | E100: {=INDEX('原始数据'!D$2:D$3689,MATCH($C100,'原始数据'!$B$2:$B$3689,0))} -> 116384 | F100: {=INDEX('原始数据'!E$2:E$3689,MATCH($C100,'原始数据'!$B$2:$B$3689,0))} -> 94621 | G100: {=INDEX('原始数据'!F$2:F$3689,MATCH($C100,'原始数据'!$B$2:$B$3689,0))} -> 9167 | H100: {=INDEX('原始数据'!G$2:G$3689,MATCH($C100,'原始数据'!$B$2:$B$3689,0))} -> 12951 | I100: {=INDEX('原始数据'!H$2:H$3689,MATCH($C100,'原始数据'!$B$2:$B$3689,0))} -> 11059 | J100: =IF(F100=0,I100*2,F100/$N$603+I100) -> 28056.699 | K100: =ROW(K100)-1 -> 99 | L100: {=INDEX(TOP3277!#REF!,MATCH(C100,TOP3277!$B$501:$B$3035,0))} -> 820
A101: 2804 | B101: 齐装网 | C101: qizuang.com | D101: {=INDEX('原始数据'!C$2:C$3689,MATCH($C101,'原始数据'!$B$2:$B$3689,0))} -> 76007 | E101: {=INDEX('原始数据'!D$2:D$3689,MATCH($C101,'原始数据'!$B$2:$B$3689,0))} -> 121413 | F101: {=INDEX('原始数据'!E$2:E$3689,MATCH($C101,'原始数据'!$B$2:$B$3689,0))} -> 98710 | G101: {=INDEX('原始数据'!F$2:F$3689,MATCH($C101,'原始数据'!$B$2:$B$3689,0))} -> 7835 | H101: {=INDEX('原始数据'!G$2:G$3689,MATCH($C101,'原始数据'!$B$2:$B$3689,0))} -> 11895 | I101: {=INDEX('原始数据'!H$2:H$3689,MATCH($C101,'原始数据'!$B$2:$B$3689,0))} -> 9865 | J101: =IF(F101=0,I101*2,F101/$N$603+I101) -> 27597.247 | K101: =ROW(K101)-1 -> 100 | L101: {=INDEX(TOP3277!#REF!,MATCH(C101,TOP3277!$B$501:$B$3035,0))} -> #N/A
...

Sheet TOP3277访问性+筛查
